{
"meta":{"test_sets":[],"test_metrics":[],"learn_metrics":[{"best_value":"Min","name":"Logloss"}],"launch_mode":"Train","parameters":"","iteration_count":1000,"learn_sets":["learn"],"name":"experiment"},
"iterations":[
{"learn":[0.6775920157],"iteration":0,"passed_time":0.1320639883,"remaining_time":131.9319243},
{"learn":[0.6618387957],"iteration":1,"passed_time":0.134946554,"remaining_time":67.33833044},
{"learn":[0.6495840564],"iteration":2,"passed_time":0.1453501717,"remaining_time":48.30470705},
{"learn":[0.637739642],"iteration":3,"passed_time":0.1483314828,"remaining_time":36.93453923},
{"learn":[0.627692464],"iteration":4,"passed_time":0.1509911625,"remaining_time":30.04724135},
{"learn":[0.6160255952],"iteration":5,"passed_time":0.1535869333,"remaining_time":25.44423529},
{"learn":[0.6056453658],"iteration":6,"passed_time":0.1561521454,"remaining_time":22.1512972},
{"learn":[0.5959897015],"iteration":7,"passed_time":0.1589761484,"remaining_time":19.71304241},
{"learn":[0.5841558531],"iteration":8,"passed_time":0.1750133561,"remaining_time":19.2709151},
{"learn":[0.5739423618],"iteration":9,"passed_time":0.1777677119,"remaining_time":17.59900348},
{"learn":[0.5619329601],"iteration":10,"passed_time":0.1899473463,"remaining_time":17.07799323},
{"learn":[0.5550486221],"iteration":11,"passed_time":0.205509879,"remaining_time":16.92031337},
{"learn":[0.5469193432],"iteration":12,"passed_time":0.207983213,"remaining_time":15.79072548},
{"learn":[0.5378304676],"iteration":13,"passed_time":0.2105988328,"remaining_time":14.83217494},
{"learn":[0.5285999773],"iteration":14,"passed_time":0.2132134169,"remaining_time":14.00101437},
{"learn":[0.5192100738],"iteration":15,"passed_time":0.215604628,"remaining_time":13.25968462},
{"learn":[0.5106732457],"iteration":16,"passed_time":0.2181963815,"remaining_time":12.61688488},
{"learn":[0.5028407143],"iteration":17,"passed_time":0.2204253456,"remaining_time":12.02542719},
{"learn":[0.4954521736],"iteration":18,"passed_time":0.222972687,"remaining_time":11.51243189},
{"learn":[0.4881690476],"iteration":19,"passed_time":0.2257889108,"remaining_time":11.06365663},
{"learn":[0.4818462556],"iteration":20,"passed_time":0.235286782,"remaining_time":10.96884569},
{"learn":[0.4757362073],"iteration":21,"passed_time":0.2380941987,"remaining_time":10.58436938},
{"learn":[0.4701982087],"iteration":22,"passed_time":0.2403079881,"remaining_time":10.20786541},
{"learn":[0.4638523947],"iteration":23,"passed_time":0.242598715,"remaining_time":9.865681076},
{"learn":[0.4561323489],"iteration":24,"passed_time":0.2449284643,"remaining_time":9.552210106},
{"learn":[0.4481516664],"iteration":25,"passed_time":0.2474919116,"remaining_time":9.271427765},
{"learn":[0.4422482209],"iteration":26,"passed_time":0.250462577,"remaining_time":9.025929163},
{"learn":[0.4370542654],"iteration":27,"passed_time":0.2657756936,"remaining_time":9.226213364},
{"learn":[0.4323964919],"iteration":28,"passed_time":0.2682541377,"remaining_time":8.981888542},
{"learn":[0.4277543855],"iteration":29,"passed_time":0.2704405381,"remaining_time":8.744244065},
{"learn":[0.423171705],"iteration":30,"passed_time":0.2727837888,"remaining_time":8.52669327},
{"learn":[0.4189139226],"iteration":31,"passed_time":0.2752518076,"remaining_time":8.326367179},
{"learn":[0.4136041461],"iteration":32,"passed_time":0.2779459998,"remaining_time":8.144660054},
{"learn":[0.4090800779],"iteration":33,"passed_time":0.2806037695,"remaining_time":7.972448273},
{"learn":[0.4044371788],"iteration":34,"passed_time":0.2834578283,"remaining_time":7.815337266},
{"learn":[0.3997780944],"iteration":35,"passed_time":0.2961861042,"remaining_time":7.93120568},
{"learn":[0.3954380005],"iteration":36,"passed_time":0.2990214212,"remaining_time":7.782638613},
{"learn":[0.3916860416],"iteration":37,"passed_time":0.3018169287,"remaining_time":7.640733827},
{"learn":[0.3877561693],"iteration":38,"passed_time":0.3045335858,"remaining_time":7.504019895},
{"learn":[0.3825424325],"iteration":39,"passed_time":0.3071222384,"remaining_time":7.370933721},
{"learn":[0.3786582078],"iteration":40,"passed_time":0.3101899102,"remaining_time":7.255417655},
{"learn":[0.3747182376],"iteration":41,"passed_time":0.3270592082,"remaining_time":7.460064797},
{"learn":[0.3708839091],"iteration":42,"passed_time":0.3297636507,"remaining_time":7.339158459},
{"learn":[0.3676234224],"iteration":43,"passed_time":0.3322715633,"remaining_time":7.219354875},
{"learn":[0.3644307213],"iteration":44,"passed_time":0.3349589056,"remaining_time":7.108572331},
{"learn":[0.3608494453],"iteration":45,"passed_time":0.3374246943,"remaining_time":6.997894748},
{"learn":[0.3573699622],"iteration":46,"passed_time":0.3396933679,"remaining_time":6.887825097},
{"learn":[0.3541647991],"iteration":47,"passed_time":0.3426966779,"remaining_time":6.796817446},
{"learn":[0.3511553892],"iteration":48,"passed_time":0.3462211307,"remaining_time":6.719516231},
{"learn":[0.3481961101],"iteration":49,"passed_time":0.3492002776,"remaining_time":6.634805274},
{"learn":[0.345123903],"iteration":50,"passed_time":0.3562258274,"remaining_time":6.628594318},
{"learn":[0.3423033212],"iteration":51,"passed_time":0.3587691154,"remaining_time":6.54063695},
{"learn":[0.3392121499],"iteration":52,"passed_time":0.3611603667,"remaining_time":6.453186174},
{"learn":[0.3357023824],"iteration":53,"passed_time":0.3635352955,"remaining_time":6.368599807},
{"learn":[0.3330365202],"iteration":54,"passed_time":0.3658084877,"remaining_time":6.285254924},
{"learn":[0.3307031583],"iteration":55,"passed_time":0.3680160547,"remaining_time":6.203699208},
{"learn":[0.3281501948],"iteration":56,"passed_time":0.3704673046,"remaining_time":6.128959092},
{"learn":[0.3256555263],"iteration":57,"passed_time":0.373167298,"remaining_time":6.060751632},
{"learn":[0.3235368397],"iteration":58,"passed_time":0.3863453667,"remaining_time":6.161881187},
{"learn":[0.3212440684],"iteration":59,"passed_time":0.4024984935,"remaining_time":6.305809731},
{"learn":[0.3191392972],"iteration":60,"passed_time":0.4051900107,"remaining_time":6.237269181},
{"learn":[0.3167779285],"iteration":61,"passed_time":0.4078087677,"remaining_time":6.169752002},
{"learn":[0.3149635801],"iteration":62,"passed_time":0.4103228578,"remaining_time":6.102738377},
{"learn":[0.3128127091],"iteration":63,"passed_time":0.412808927,"remaining_time":6.037330558},
{"learn":[0.3107433771],"iteration":64,"passed_time":0.4163376035,"remaining_time":5.988856296},
{"learn":[0.3091167369],"iteration":65,"passed_time":0.4188982252,"remaining_time":5.928044581},
{"learn":[0.3065297269],"iteration":66,"passed_time":0.4216789139,"remaining_time":5.872036219},
{"learn":[0.3045522336],"iteration":67,"passed_time":0.4246270593,"remaining_time":5.819888519},
{"learn":[0.3029051475],"iteration":68,"passed_time":0.4316471984,"remaining_time":5.824109301},
{"learn":[0.3012363648],"iteration":69,"passed_time":0.4463189086,"remaining_time":5.9296655},
{"learn":[0.2991642079],"iteration":70,"passed_time":0.4491313653,"remaining_time":5.876662512},
{"learn":[0.2973553834],"iteration":71,"passed_time":0.4616607575,"remaining_time":5.950294208},
{"learn":[0.2957710001],"iteration":72,"passed_time":0.4768832999,"remaining_time":6.055764644},
{"learn":[0.293506249],"iteration":73,"passed_time":0.4796745946,"remaining_time":6.002414522},
{"learn":[0.2913856669],"iteration":74,"passed_time":0.4918531778,"remaining_time":6.066189193},
{"learn":[0.2894651752],"iteration":75,"passed_time":0.4947779106,"remaining_time":6.015457755},
{"learn":[0.2874644239],"iteration":76,"passed_time":0.5063096447,"remaining_time":6.069140286},
{"learn":[0.2862373489],"iteration":77,"passed_time":0.5213441846,"remaining_time":6.162555618},
{"learn":[0.2850878887],"iteration":78,"passed_time":0.5371930688,"remaining_time":6.262719195},
{"learn":[0.2835467481],"iteration":79,"passed_time":0.5526582419,"remaining_time":6.355569782},
{"learn":[0.2816337084],"iteration":80,"passed_time":0.5555110439,"remaining_time":6.302649992},
{"learn":[0.2796880284],"iteration":81,"passed_time":0.5584652063,"remaining_time":6.25208609},
{"learn":[0.2787619303],"iteration":82,"passed_time":0.5667687895,"remaining_time":6.261770843},
{"learn":[0.277364296],"iteration":83,"passed_time":0.5829740353,"remaining_time":6.357193051},
{"learn":[0.2761287104],"iteration":84,"passed_time":0.5979497686,"remaining_time":6.436753391},
{"learn":[0.275299383],"iteration":85,"passed_time":0.6008790867,"remaining_time":6.386087037},
{"learn":[0.2738080143],"iteration":86,"passed_time":0.6035864046,"remaining_time":6.334188361},
{"learn":[0.2729355465],"iteration":87,"passed_time":0.6064152585,"remaining_time":6.284667224},
{"learn":[0.2720380122],"iteration":88,"passed_time":0.6092018282,"remaining_time":6.235762533},
{"learn":[0.2709171186],"iteration":89,"passed_time":0.6121856146,"remaining_time":6.18987677},
{"learn":[0.2699465648],"iteration":90,"passed_time":0.6263921321,"remaining_time":6.257037891},
{"learn":[0.2687839381],"iteration":91,"passed_time":0.6426232545,"remaining_time":6.342412121},
{"learn":[0.2676468434],"iteration":92,"passed_time":0.6456843639,"remaining_time":6.297158259},
{"learn":[0.2660819454],"iteration":93,"passed_time":0.6486835452,"remaining_time":6.252205233},
{"learn":[0.2647331063],"iteration":94,"passed_time":0.6578470794,"remaining_time":6.26685902},
{"learn":[0.2638619261],"iteration":95,"passed_time":0.6604635071,"remaining_time":6.219364692},
{"learn":[0.2631286166],"iteration":96,"passed_time":0.6726210023,"remaining_time":6.261616134},
{"learn":[0.2620572581],"iteration":97,"passed_time":0.6753188414,"remaining_time":6.215689744},
{"learn":[0.2613113189],"iteration":98,"passed_time":0.6785390766,"remaining_time":6.17539099},
{"learn":[0.2603777765],"iteration":99,"passed_time":0.6812409787,"remaining_time":6.131168809},
{"learn":[0.2593929126],"iteration":100,"passed_time":0.684125478,"remaining_time":6.089394106},
{"learn":[0.2584395379],"iteration":101,"passed_time":0.7024380718,"remaining_time":6.184209691},
{"learn":[0.2576430156],"iteration":102,"passed_time":0.7339707022,"remaining_time":6.391958445},
{"learn":[0.2565125795],"iteration":103,"passed_time":0.7499480016,"remaining_time":6.461090476},
{"learn":[0.2553868157],"iteration":104,"passed_time":0.7530623466,"remaining_time":6.418960002},
{"learn":[0.2543836903],"iteration":105,"passed_time":0.7558986903,"remaining_time":6.37522103},
{"learn":[0.2536384229],"iteration":106,"passed_time":0.7584289024,"remaining_time":6.329691681},
{"learn":[0.2526684994],"iteration":107,"passed_time":0.7611841397,"remaining_time":6.286817154},
{"learn":[0.2516243987],"iteration":108,"passed_time":0.7638643191,"remaining_time":6.244065214},
{"learn":[0.2503594165],"iteration":109,"passed_time":0.766433949,"remaining_time":6.201147405},
{"learn":[0.2495523932],"iteration":110,"passed_time":0.7805272824,"remaining_time":6.251250037},
{"learn":[0.2488678061],"iteration":111,"passed_time":0.7832284581,"remaining_time":6.209882775},
{"learn":[0.2480420304],"iteration":112,"passed_time":0.7862036472,"remaining_time":6.171350753},
{"learn":[0.2473521786],"iteration":113,"passed_time":0.7890137589,"remaining_time":6.132159565},
{"learn":[0.2465510286],"iteration":114,"passed_time":0.7943430004,"remaining_time":6.112987438},
{"learn":[0.2459415811],"iteration":115,"passed_time":0.8093290188,"remaining_time":6.167645281},
{"learn":[0.2453100978],"iteration":116,"passed_time":0.8125104066,"remaining_time":6.132022983},
{"learn":[0.2445435059],"iteration":117,"passed_time":0.815828195,"remaining_time":6.097970067},
{"learn":[0.243813207],"iteration":118,"passed_time":0.8183516182,"remaining_time":6.058552737},
{"learn":[0.2430693879],"iteration":119,"passed_time":0.8245383546,"remaining_time":6.046614601},
{"learn":[0.2422893927],"iteration":120,"passed_time":0.8273192384,"remaining_time":6.010029839},
{"learn":[0.2415134789],"iteration":121,"passed_time":0.8301375213,"remaining_time":5.974268391},
{"learn":[0.2407969404],"iteration":122,"passed_time":0.839507555,"remaining_time":5.98575712},
{"learn":[0.2402331226],"iteration":123,"passed_time":0.8549898023,"remaining_time":6.040089248},
{"learn":[0.2396970099],"iteration":124,"passed_time":0.8703527483,"remaining_time":6.092469238},
{"learn":[0.2391647592],"iteration":125,"passed_time":0.8736070254,"remaining_time":6.059782065},
{"learn":[0.2384725924],"iteration":126,"passed_time":0.8764356839,"remaining_time":6.024632693},
{"learn":[0.2377511979],"iteration":127,"passed_time":0.8791848999,"remaining_time":5.98944713},
{"learn":[0.2371184253],"iteration":128,"passed_time":0.8819316459,"remaining_time":5.95474778},
{"learn":[0.2366479715],"iteration":129,"passed_time":0.8848109348,"remaining_time":5.921427025},
{"learn":[0.2361252416],"iteration":130,"passed_time":0.8874609942,"remaining_time":5.887050412},
{"learn":[0.2353822131],"iteration":131,"passed_time":0.9012703696,"remaining_time":5.926535461},
{"learn":[0.2349400258],"iteration":132,"passed_time":0.9152696516,"remaining_time":5.966457052},
{"learn":[0.2341689418],"iteration":133,"passed_time":0.9179647853,"remaining_time":5.932518687},
{"learn":[0.2335237126],"iteration":134,"passed_time":0.921010895,"remaining_time":5.901292031},
{"learn":[0.2332028525],"iteration":135,"passed_time":0.9242718506,"remaining_time":5.871844698},
{"learn":[0.2325872099],"iteration":136,"passed_time":0.927274454,"remaining_time":5.841152217},
{"learn":[0.232120551],"iteration":137,"passed_time":0.9300545659,"remaining_time":5.809471274},
{"learn":[0.2316096285],"iteration":138,"passed_time":0.9330460576,"remaining_time":5.779515508},
{"learn":[0.2308723518],"iteration":139,"passed_time":0.9466811775,"remaining_time":5.815327233},
{"learn":[0.2303022849],"iteration":140,"passed_time":0.9495374557,"remaining_time":5.784770741},
{"learn":[0.2297526396],"iteration":141,"passed_time":0.9523504579,"remaining_time":5.754342907},
{"learn":[0.2292099745],"iteration":142,"passed_time":0.9553212535,"remaining_time":5.725246953},
{"learn":[0.2287163876],"iteration":143,"passed_time":0.9582067544,"remaining_time":5.696006818},
{"learn":[0.2282489071],"iteration":144,"passed_time":0.9608601209,"remaining_time":5.665761403},
{"learn":[0.2276528863],"iteration":145,"passed_time":0.9782581013,"remaining_time":5.722139853},
{"learn":[0.2271207125],"iteration":146,"passed_time":0.9942785407,"remaining_time":5.769521056},
{"learn":[0.2265035758],"iteration":147,"passed_time":0.9971720828,"remaining_time":5.740477125},
{"learn":[0.2261415293],"iteration":148,"passed_time":1.000006257,"remaining_time":5.711445132},
{"learn":[0.2257185648],"iteration":149,"passed_time":1.015616283,"remaining_time":5.755158936},
{"learn":[0.2252315263],"iteration":150,"passed_time":1.026399959,"remaining_time":5.770950765},
{"learn":[0.2246682095],"iteration":151,"passed_time":1.03380215,"remaining_time":5.767527787},
{"learn":[0.2240821276],"iteration":152,"passed_time":1.046699439,"remaining_time":5.794473365},
{"learn":[0.2235894143],"iteration":153,"passed_time":1.05148432,"remaining_time":5.776335937},
{"learn":[0.2232220124],"iteration":154,"passed_time":1.071009653,"remaining_time":5.838730045},
{"learn":[0.2227819019],"iteration":155,"passed_time":1.08755817,"remaining_time":5.883968562},
{"learn":[0.2222480349],"iteration":156,"passed_time":1.100087688,"remaining_time":5.90684026},
{"learn":[0.2218723409],"iteration":157,"passed_time":1.102553266,"remaining_time":5.875631964},
{"learn":[0.2214996786],"iteration":158,"passed_time":1.105097862,"remaining_time":5.845203155},
{"learn":[0.2210403461],"iteration":159,"passed_time":1.107416078,"remaining_time":5.81393441},
{"learn":[0.2208355615],"iteration":160,"passed_time":1.11007468,"remaining_time":5.784799107},
{"learn":[0.2203328487],"iteration":161,"passed_time":1.112457314,"remaining_time":5.754563142},
{"learn":[0.2200304858],"iteration":162,"passed_time":1.114850384,"remaining_time":5.724722522},
{"learn":[0.219371348],"iteration":163,"passed_time":1.130877902,"remaining_time":5.76471906},
{"learn":[0.2192337008],"iteration":164,"passed_time":1.133792415,"remaining_time":5.737676769},
{"learn":[0.2190341242],"iteration":165,"passed_time":1.136939735,"remaining_time":5.712094814},
{"learn":[0.218672399],"iteration":166,"passed_time":1.144963555,"remaining_time":5.711105636},
{"learn":[0.2181800745],"iteration":167,"passed_time":1.148119392,"remaining_time":5.685924609},
{"learn":[0.2176247136],"iteration":168,"passed_time":1.17584264,"remaining_time":5.781806118},
{"learn":[0.2173142079],"iteration":169,"passed_time":1.178605033,"remaining_time":5.754365747},
{"learn":[0.2169887777],"iteration":170,"passed_time":1.181139277,"remaining_time":5.726107959},
{"learn":[0.2167775409],"iteration":171,"passed_time":1.183759392,"remaining_time":5.698562656},
{"learn":[0.2165774537],"iteration":172,"passed_time":1.186112794,"remaining_time":5.670030523},
{"learn":[0.2161515943],"iteration":173,"passed_time":1.188931192,"remaining_time":5.644006693},
{"learn":[0.2157505867],"iteration":174,"passed_time":1.207162951,"remaining_time":5.690911052},
{"learn":[0.2153753165],"iteration":175,"passed_time":1.222251452,"remaining_time":5.72235907},
{"learn":[0.2150497199],"iteration":176,"passed_time":1.22561423,"remaining_time":5.698759949},
{"learn":[0.2146403183],"iteration":177,"passed_time":1.228266123,"remaining_time":5.672105354},
{"learn":[0.2142522527],"iteration":178,"passed_time":1.236896559,"remaining_time":5.673140085},
{"learn":[0.2138960055],"iteration":179,"passed_time":1.239340365,"remaining_time":5.645883884},
{"learn":[0.2136980393],"iteration":180,"passed_time":1.24195803,"remaining_time":5.619688545},
{"learn":[0.2132999345],"iteration":181,"passed_time":1.24441941,"remaining_time":5.593049876},
{"learn":[0.2128624216],"iteration":182,"passed_time":1.247280388,"remaining_time":5.568459437},
{"learn":[0.2123991128],"iteration":183,"passed_time":1.251373007,"remaining_time":5.54956725},
{"learn":[0.2120441583],"iteration":184,"passed_time":1.254124663,"remaining_time":5.524927571},
{"learn":[0.2116393328],"iteration":185,"passed_time":1.256854882,"remaining_time":5.500429429},
{"learn":[0.2111952726],"iteration":186,"passed_time":1.259543072,"remaining_time":5.475981376},
{"learn":[0.2108258815],"iteration":187,"passed_time":1.266813682,"remaining_time":5.471556968},
{"learn":[0.210536993],"iteration":188,"passed_time":1.28157238,"remaining_time":5.499233864},
{"learn":[0.2099887305],"iteration":189,"passed_time":1.284361996,"remaining_time":5.475437982},
{"learn":[0.2096158451],"iteration":190,"passed_time":1.286928801,"remaining_time":5.450918324},
{"learn":[0.2091861233],"iteration":191,"passed_time":1.289376854,"remaining_time":5.426127594},
{"learn":[0.2088858642],"iteration":192,"passed_time":1.291725676,"remaining_time":5.401153476},
{"learn":[0.2086005343],"iteration":193,"passed_time":1.294523098,"remaining_time":5.378276378},
{"learn":[0.2082280281],"iteration":194,"passed_time":1.310787211,"remaining_time":5.411198486},
{"learn":[0.2079503677],"iteration":195,"passed_time":1.313290689,"remaining_time":5.387172011},
{"learn":[0.2076335827],"iteration":196,"passed_time":1.326095734,"remaining_time":5.405354692},
{"learn":[0.2072427229],"iteration":197,"passed_time":1.328766444,"remaining_time":5.382175192},
{"learn":[0.2070179235],"iteration":198,"passed_time":1.342364041,"remaining_time":5.403183903},
{"learn":[0.2064610507],"iteration":199,"passed_time":1.345089884,"remaining_time":5.380359538},
{"learn":[0.2061425838],"iteration":200,"passed_time":1.348077643,"remaining_time":5.358776301},
{"learn":[0.2059735904],"iteration":201,"passed_time":1.357370554,"remaining_time":5.362285652},
{"learn":[0.2056115376],"iteration":202,"passed_time":1.360204874,"remaining_time":5.340311745},
{"learn":[0.2052391013],"iteration":203,"passed_time":1.373561341,"remaining_time":5.359582487},
{"learn":[0.2049286477],"iteration":204,"passed_time":1.375735446,"remaining_time":5.33516917},
{"learn":[0.2047769413],"iteration":205,"passed_time":1.378446547,"remaining_time":5.313041544},
{"learn":[0.2045295858],"iteration":206,"passed_time":1.380820891,"remaining_time":5.289811433},
{"learn":[0.2041733473],"iteration":207,"passed_time":1.383627063,"remaining_time":5.268426126},
{"learn":[0.204011083],"iteration":208,"passed_time":1.387937806,"remaining_time":5.25291294},
{"learn":[0.203809966],"iteration":209,"passed_time":1.390297665,"remaining_time":5.230167406},
{"learn":[0.2035690656],"iteration":210,"passed_time":1.39275881,"remaining_time":5.207993844},
{"learn":[0.2033295835],"iteration":211,"passed_time":1.395184319,"remaining_time":5.18587379},
{"learn":[0.2031607586],"iteration":212,"passed_time":1.397448794,"remaining_time":5.163343665},
{"learn":[0.2029602226],"iteration":213,"passed_time":1.399813883,"remaining_time":5.141372486},
{"learn":[0.2023135799],"iteration":214,"passed_time":1.402275112,"remaining_time":5.119934712},
{"learn":[0.2020010465],"iteration":215,"passed_time":1.404371379,"remaining_time":5.097347967},
{"learn":[0.2017859406],"iteration":216,"passed_time":1.406692827,"remaining_time":5.075762596},
{"learn":[0.2015192632],"iteration":217,"passed_time":1.408841207,"remaining_time":5.053733136},
{"learn":[0.2013213122],"iteration":218,"passed_time":1.411178335,"remaining_time":5.032558356},
{"learn":[0.2011654787],"iteration":219,"passed_time":1.413878173,"remaining_time":5.012840797},
{"learn":[0.2009718079],"iteration":220,"passed_time":1.416271514,"remaining_time":4.992196876},
{"learn":[0.20072518],"iteration":221,"passed_time":1.418719628,"remaining_time":4.971909326},
{"learn":[0.2003549709],"iteration":222,"passed_time":1.420959369,"remaining_time":4.951055737},
{"learn":[0.2000576984],"iteration":223,"passed_time":1.423438942,"remaining_time":4.93119919},
{"learn":[0.1999037448],"iteration":224,"passed_time":1.425976727,"remaining_time":4.911697616},
{"learn":[0.1996180113],"iteration":225,"passed_time":1.428008145,"remaining_time":4.890611965},
{"learn":[0.1992713458],"iteration":226,"passed_time":1.430400834,"remaining_time":4.870924425},
{"learn":[0.1991561144],"iteration":227,"passed_time":1.432675283,"remaining_time":4.85098824},
{"learn":[0.1988786395],"iteration":228,"passed_time":1.434952433,"remaining_time":4.831215397},
{"learn":[0.1985848592],"iteration":229,"passed_time":1.437271889,"remaining_time":4.811736323},
{"learn":[0.1981913104],"iteration":230,"passed_time":1.439602168,"remaining_time":4.792441849},
{"learn":[0.1979087189],"iteration":231,"passed_time":1.442332426,"remaining_time":4.774617687},
{"learn":[0.1976512919],"iteration":232,"passed_time":1.444698252,"remaining_time":4.755723431},
{"learn":[0.1973611361],"iteration":233,"passed_time":1.447393612,"remaining_time":4.738049173},
{"learn":[0.1972243968],"iteration":234,"passed_time":1.463497742,"remaining_time":4.764152222},
{"learn":[0.1969805133],"iteration":235,"passed_time":1.466164775,"remaining_time":4.746397829},
{"learn":[0.1965641916],"iteration":236,"passed_time":1.478751936,"remaining_time":4.760707711},
{"learn":[0.1963133923],"iteration":237,"passed_time":1.481378094,"remaining_time":4.742899611},
{"learn":[0.196154698],"iteration":238,"passed_time":1.483843532,"remaining_time":4.724706811},
{"learn":[0.1959289808],"iteration":239,"passed_time":1.494498758,"remaining_time":4.732579402},
{"learn":[0.195615666],"iteration":240,"passed_time":1.510545642,"remaining_time":4.757278597},
{"learn":[0.1954268076],"iteration":241,"passed_time":1.525396375,"remaining_time":4.777894432},
{"learn":[0.1951833603],"iteration":242,"passed_time":1.528325147,"remaining_time":4.761078751},
{"learn":[0.1950021093],"iteration":243,"passed_time":1.5318364,"remaining_time":4.746181632},
{"learn":[0.1947150763],"iteration":244,"passed_time":1.539336766,"remaining_time":4.743670441},
{"learn":[0.1942602438],"iteration":245,"passed_time":1.541814563,"remaining_time":4.725724312},
{"learn":[0.1939869411],"iteration":246,"passed_time":1.554763909,"remaining_time":4.739826815},
{"learn":[0.1937280805],"iteration":247,"passed_time":1.570078203,"remaining_time":4.760882293},
{"learn":[0.1934280786],"iteration":248,"passed_time":1.572691695,"remaining_time":4.743339208},
{"learn":[0.1930730391],"iteration":249,"passed_time":1.575128451,"remaining_time":4.725385353},
{"learn":[0.1928529986],"iteration":250,"passed_time":1.577508891,"remaining_time":4.707387089},
{"learn":[0.192603455],"iteration":251,"passed_time":1.580099167,"remaining_time":4.690135622},
{"learn":[0.1923875888],"iteration":252,"passed_time":1.582232076,"remaining_time":4.671649647},
{"learn":[0.1921831347],"iteration":253,"passed_time":1.584755244,"remaining_time":4.654438629},
{"learn":[0.1919958766],"iteration":254,"passed_time":1.587010411,"remaining_time":4.636559829},
{"learn":[0.1918217098],"iteration":255,"passed_time":1.589520096,"remaining_time":4.61954278},
{"learn":[0.1915708828],"iteration":256,"passed_time":1.591616353,"remaining_time":4.601443386},
{"learn":[0.1913622996],"iteration":257,"passed_time":1.593665666,"remaining_time":4.58333304},
{"learn":[0.1911224396],"iteration":258,"passed_time":1.595979398,"remaining_time":4.56610322},
{"learn":[0.1909391562],"iteration":259,"passed_time":1.598567299,"remaining_time":4.549768466},
{"learn":[0.1907463425],"iteration":260,"passed_time":1.615257792,"remaining_time":4.573469381},
{"learn":[0.1905081298],"iteration":261,"passed_time":1.617557482,"remaining_time":4.556326037},
{"learn":[0.1903080474],"iteration":262,"passed_time":1.620009163,"remaining_time":4.539721495},
{"learn":[0.1901468419],"iteration":263,"passed_time":1.622078787,"remaining_time":4.522159041},
{"learn":[0.1899647565],"iteration":264,"passed_time":1.624508815,"remaining_time":4.505713128},
{"learn":[0.1898406296],"iteration":265,"passed_time":1.626786837,"remaining_time":4.488953151},
{"learn":[0.1896166571],"iteration":266,"passed_time":1.629334098,"remaining_time":4.473040801},
{"learn":[0.189362604],"iteration":267,"passed_time":1.632094045,"remaining_time":4.457809107},
{"learn":[0.1891074922],"iteration":268,"passed_time":1.634609973,"remaining_time":4.442007027},
{"learn":[0.1889266133],"iteration":269,"passed_time":1.637187289,"remaining_time":4.426469337},
{"learn":[0.1888476238],"iteration":270,"passed_time":1.645035323,"remaining_time":4.425205722},
{"learn":[0.1886198168],"iteration":271,"passed_time":1.647475787,"remaining_time":4.409420489},
{"learn":[0.1883767678],"iteration":272,"passed_time":1.649888105,"remaining_time":4.393658068},
{"learn":[0.1882343206],"iteration":273,"passed_time":1.652065693,"remaining_time":4.377371142},
{"learn":[0.1878857519],"iteration":274,"passed_time":1.654504318,"remaining_time":4.36187502},
{"learn":[0.1875576973],"iteration":275,"passed_time":1.656943284,"remaining_time":4.346474411},
{"learn":[0.1874246743],"iteration":276,"passed_time":1.662032264,"remaining_time":4.338084212},
{"learn":[0.1872233399],"iteration":277,"passed_time":1.664901303,"remaining_time":4.323952304},
{"learn":[0.1869884547],"iteration":278,"passed_time":1.667576637,"remaining_time":4.309400557},
{"learn":[0.1867071111],"iteration":279,"passed_time":1.676207269,"remaining_time":4.310247264},
{"learn":[0.186279089],"iteration":280,"passed_time":1.691235817,"remaining_time":4.327396984},
{"learn":[0.1860546929],"iteration":281,"passed_time":1.693505808,"remaining_time":4.311833936},
{"learn":[0.1858388413],"iteration":282,"passed_time":1.695768845,"remaining_time":4.296347215},
{"learn":[0.1857018894],"iteration":283,"passed_time":1.698127301,"remaining_time":4.281194181},
{"learn":[0.1855814653],"iteration":284,"passed_time":1.700403494,"remaining_time":4.265924555},
{"learn":[0.1853792614],"iteration":285,"passed_time":1.706774141,"remaining_time":4.26096761},
{"learn":[0.1851908598],"iteration":286,"passed_time":1.709428378,"remaining_time":4.246768061},
{"learn":[0.184976504],"iteration":287,"passed_time":1.711979551,"remaining_time":4.23239389},
{"learn":[0.1846558516],"iteration":288,"passed_time":1.714619431,"remaining_time":4.218319776},
{"learn":[0.1844495214],"iteration":289,"passed_time":1.721544496,"remaining_time":4.214815835},
{"learn":[0.1843031277],"iteration":290,"passed_time":1.736512534,"remaining_time":4.23088449},
{"learn":[0.1839140449],"iteration":291,"passed_time":1.739129914,"remaining_time":4.216794448},
{"learn":[0.1834826911],"iteration":292,"passed_time":1.741691437,"remaining_time":4.202647939},
{"learn":[0.1833192284],"iteration":293,"passed_time":1.744308657,"remaining_time":4.188713985},
{"learn":[0.1830431235],"iteration":294,"passed_time":1.746571323,"remaining_time":4.174009433},
{"learn":[0.1827910453],"iteration":295,"passed_time":1.749023185,"remaining_time":4.159838926},
{"learn":[0.1825319869],"iteration":296,"passed_time":1.751407587,"remaining_time":4.145587655},
{"learn":[0.1822917954],"iteration":297,"passed_time":1.753586572,"remaining_time":4.130932127},
{"learn":[0.1819304319],"iteration":298,"passed_time":1.756115171,"remaining_time":4.117179715},
{"learn":[0.1816308923],"iteration":299,"passed_time":1.766630801,"remaining_time":4.122138536},
{"learn":[0.1814973549],"iteration":300,"passed_time":1.781933272,"remaining_time":4.13811082},
{"learn":[0.1811670598],"iteration":301,"passed_time":1.797042795,"remaining_time":4.153430036},
{"learn":[0.1809160899],"iteration":302,"passed_time":1.799542842,"remaining_time":4.139542445},
{"learn":[0.1806284569],"iteration":303,"passed_time":1.802063129,"remaining_time":4.125776111},
{"learn":[0.180420276],"iteration":304,"passed_time":1.804788933,"remaining_time":4.112551832},
{"learn":[0.1802375625],"iteration":305,"passed_time":1.806942684,"remaining_time":4.098098766},
{"learn":[0.1801005213],"iteration":306,"passed_time":1.809423863,"remaining_time":4.084464942},
{"learn":[0.1798841584],"iteration":307,"passed_time":1.8118383,"remaining_time":4.070753584},
{"learn":[0.1795905],"iteration":308,"passed_time":1.814615276,"remaining_time":4.057926071},
{"learn":[0.1793680373],"iteration":309,"passed_time":1.816867191,"remaining_time":4.043994716},
{"learn":[0.1791507292],"iteration":310,"passed_time":1.819082834,"remaining_time":4.030058112},
{"learn":[0.1788294628],"iteration":311,"passed_time":1.821512342,"remaining_time":4.01666824},
{"learn":[0.1786278849],"iteration":312,"passed_time":1.823774948,"remaining_time":4.002982074},
{"learn":[0.1783816592],"iteration":313,"passed_time":1.826417618,"remaining_time":3.990198999},
{"learn":[0.1780759821],"iteration":314,"passed_time":1.828946562,"remaining_time":3.977233},
{"learn":[0.1777814484],"iteration":315,"passed_time":1.831250435,"remaining_time":3.963845878},
{"learn":[0.1775896977],"iteration":316,"passed_time":1.83376227,"remaining_time":3.950976752},
{"learn":[0.1774128676],"iteration":317,"passed_time":1.839852115,"remaining_time":3.945846359},
{"learn":[0.177069204],"iteration":318,"passed_time":1.842210686,"remaining_time":3.932744442},
{"learn":[0.1768340084],"iteration":319,"passed_time":1.8446437,"remaining_time":3.919867863},
{"learn":[0.1765939493],"iteration":320,"passed_time":1.846896006,"remaining_time":3.906674106},
{"learn":[0.1763476536],"iteration":321,"passed_time":1.849264487,"remaining_time":3.893792927},
{"learn":[0.1762394858],"iteration":322,"passed_time":1.851683629,"remaining_time":3.881083024},
{"learn":[0.1761358901],"iteration":323,"passed_time":1.870694963,"remaining_time":3.903054923},
{"learn":[0.1758171838],"iteration":324,"passed_time":1.885804438,"remaining_time":3.916670755},
{"learn":[0.1756751],"iteration":325,"passed_time":1.888168038,"remaining_time":3.903758459},
{"learn":[0.1754804508],"iteration":326,"passed_time":1.900886385,"remaining_time":3.912221826},
{"learn":[0.1754056342],"iteration":327,"passed_time":1.916463576,"remaining_time":3.926413179},
{"learn":[0.1751629267],"iteration":328,"passed_time":1.919645299,"remaining_time":3.915142844},
{"learn":[0.1750264633],"iteration":329,"passed_time":1.930738795,"remaining_time":3.919984825},
{"learn":[0.1747720699],"iteration":330,"passed_time":1.946231192,"remaining_time":3.933621352},
{"learn":[0.1745405829],"iteration":331,"passed_time":1.948589338,"remaining_time":3.920655655},
{"learn":[0.1743962673],"iteration":332,"passed_time":1.951153998,"remaining_time":3.908167317},
{"learn":[0.1742259695],"iteration":333,"passed_time":1.953643765,"remaining_time":3.895589065},
{"learn":[0.1740008965],"iteration":334,"passed_time":1.956259251,"remaining_time":3.883320603},
{"learn":[0.173917187],"iteration":335,"passed_time":1.958937721,"remaining_time":3.871234068},
{"learn":[0.1736063139],"iteration":336,"passed_time":1.976406016,"remaining_time":3.888300263},
{"learn":[0.1734502082],"iteration":337,"passed_time":1.990761164,"remaining_time":3.899064764},
{"learn":[0.173239111],"iteration":338,"passed_time":1.993290143,"remaining_time":3.886621783},
{"learn":[0.1729861171],"iteration":339,"passed_time":1.995784563,"remaining_time":3.874170034},
{"learn":[0.1727244501],"iteration":340,"passed_time":1.997969866,"remaining_time":3.861179301},
{"learn":[0.1724971163],"iteration":341,"passed_time":2.000437369,"remaining_time":3.848794704},
{"learn":[0.1723605431],"iteration":342,"passed_time":2.002613188,"remaining_time":3.835909226},
{"learn":[0.1721099562],"iteration":343,"passed_time":2.004969942,"remaining_time":3.823431052},
{"learn":[0.1719649558],"iteration":344,"passed_time":2.007171591,"remaining_time":3.810717079},
{"learn":[0.171669189],"iteration":345,"passed_time":2.0095666,"remaining_time":3.798429353},
{"learn":[0.1714869998],"iteration":346,"passed_time":2.011918197,"remaining_time":3.786116953},
{"learn":[0.1712969691],"iteration":347,"passed_time":2.01397246,"remaining_time":3.773304724},
{"learn":[0.1710720111],"iteration":348,"passed_time":2.016452818,"remaining_time":3.761348953},
{"learn":[0.1710316268],"iteration":349,"passed_time":2.018354784,"remaining_time":3.748373171},
{"learn":[0.1709165999],"iteration":350,"passed_time":2.020610362,"remaining_time":3.736114315},
{"learn":[0.1708044265],"iteration":351,"passed_time":2.022913919,"remaining_time":3.724000623},
{"learn":[0.1706538472],"iteration":352,"passed_time":2.025263582,"remaining_time":3.712027019},
{"learn":[0.1704494119],"iteration":353,"passed_time":2.035840103,"remaining_time":3.71512064},
{"learn":[0.1703159112],"iteration":354,"passed_time":2.038630987,"remaining_time":3.703991511},
{"learn":[0.1701671464],"iteration":355,"passed_time":2.041130493,"remaining_time":3.692382127},
{"learn":[0.1699303148],"iteration":356,"passed_time":2.043435563,"remaining_time":3.680473577},
{"learn":[0.169817341],"iteration":357,"passed_time":2.045939959,"remaining_time":3.668976127},
{"learn":[0.1696408676],"iteration":358,"passed_time":2.048365763,"remaining_time":3.657388452},
{"learn":[0.1693687103],"iteration":359,"passed_time":2.050802515,"remaining_time":3.645871137},
{"learn":[0.1692103284],"iteration":360,"passed_time":2.05342019,"remaining_time":3.634724381},
{"learn":[0.1689847944],"iteration":361,"passed_time":2.055933894,"remaining_time":3.623441504},
{"learn":[0.1688042375],"iteration":362,"passed_time":2.058512423,"remaining_time":3.612320698},
{"learn":[0.1685798971],"iteration":363,"passed_time":2.060821645,"remaining_time":3.600776282},
{"learn":[0.1683205284],"iteration":364,"passed_time":2.063194049,"remaining_time":3.589392387},
{"learn":[0.1682307295],"iteration":365,"passed_time":2.065419752,"remaining_time":3.577803614},
{"learn":[0.1680717092],"iteration":366,"passed_time":2.067682769,"remaining_time":3.566330225},
{"learn":[0.1678604164],"iteration":367,"passed_time":2.06998319,"remaining_time":3.55497113},
{"learn":[0.1677281797],"iteration":368,"passed_time":2.072082442,"remaining_time":3.54331713},
{"learn":[0.167572645],"iteration":369,"passed_time":2.074375949,"remaining_time":3.532045536},
{"learn":[0.1674777397],"iteration":370,"passed_time":2.07663568,"remaining_time":3.520765075},
{"learn":[0.1673225893],"iteration":371,"passed_time":2.078860311,"remaining_time":3.509473858},
{"learn":[0.1672178056],"iteration":372,"passed_time":2.081347138,"remaining_time":3.498671998},
{"learn":[0.1669241226],"iteration":373,"passed_time":2.083781027,"remaining_time":3.487825998},
{"learn":[0.1667372816],"iteration":374,"passed_time":2.086487834,"remaining_time":3.477479724},
{"learn":[0.1665526682],"iteration":375,"passed_time":2.095356358,"remaining_time":3.477399914},
{"learn":[0.1663198158],"iteration":376,"passed_time":2.111865846,"remaining_time":3.489900324},
{"learn":[0.1659359163],"iteration":377,"passed_time":2.114446744,"remaining_time":3.47932771},
{"learn":[0.1657818353],"iteration":378,"passed_time":2.117073617,"remaining_time":3.468872601},
{"learn":[0.1655652093],"iteration":379,"passed_time":2.126126491,"remaining_time":3.468943222},
{"learn":[0.1652939707],"iteration":380,"passed_time":2.128599028,"remaining_time":3.458275062},
{"learn":[0.165050356],"iteration":381,"passed_time":2.13082912,"remaining_time":3.447257581},
{"learn":[0.1649193712],"iteration":382,"passed_time":2.13316432,"remaining_time":3.436455315},
{"learn":[0.1647389229],"iteration":383,"passed_time":2.135482522,"remaining_time":3.425669879},
{"learn":[0.1645136691],"iteration":384,"passed_time":2.137646192,"remaining_time":3.414681579},
{"learn":[0.1644164285],"iteration":385,"passed_time":2.139860527,"remaining_time":3.403819595},
{"learn":[0.1642192369],"iteration":386,"passed_time":2.1424873,"remaining_time":3.393655595},
{"learn":[0.1640430786],"iteration":387,"passed_time":2.144955083,"remaining_time":3.383279667},
{"learn":[0.1639173089],"iteration":388,"passed_time":2.147230294,"remaining_time":3.372641928},
{"learn":[0.1636803086],"iteration":389,"passed_time":2.149648805,"remaining_time":3.362271207},
{"learn":[0.1633882103],"iteration":390,"passed_time":2.152069389,"remaining_time":3.351944394},
{"learn":[0.1632346501],"iteration":391,"passed_time":2.154471592,"remaining_time":3.341629408},
{"learn":[0.1630896162],"iteration":392,"passed_time":2.156932938,"remaining_time":3.331446039},
{"learn":[0.1630236371],"iteration":393,"passed_time":2.170217327,"remaining_time":3.337948478},
{"learn":[0.162879408],"iteration":394,"passed_time":2.172530989,"remaining_time":3.327547464},
{"learn":[0.1627365037],"iteration":395,"passed_time":2.174986558,"remaining_time":3.31740374},
{"learn":[0.1625603494],"iteration":396,"passed_time":2.177313938,"remaining_time":3.307104042},
{"learn":[0.1623769845],"iteration":397,"passed_time":2.179563598,"remaining_time":3.29672685},
{"learn":[0.1622181442],"iteration":398,"passed_time":2.182335584,"remaining_time":3.287177159},
{"learn":[0.1619780959],"iteration":399,"passed_time":2.200121349,"remaining_time":3.300182024},
{"learn":[0.161732401],"iteration":400,"passed_time":2.214866485,"remaining_time":3.308491333},
{"learn":[0.1616454154],"iteration":401,"passed_time":2.230265918,"remaining_time":3.317659251},
{"learn":[0.1615589273],"iteration":402,"passed_time":2.245018268,"remaining_time":3.325746665},
{"learn":[0.1614465461],"iteration":403,"passed_time":2.260744609,"remaining_time":3.335157889},
{"learn":[0.161288265],"iteration":404,"passed_time":2.263070581,"remaining_time":3.324758014},
{"learn":[0.161130596],"iteration":405,"passed_time":2.26540281,"remaining_time":3.314407067},
{"learn":[0.1609743904],"iteration":406,"passed_time":2.267642751,"remaining_time":3.30396106},
{"learn":[0.1607840782],"iteration":407,"passed_time":2.270029489,"remaining_time":3.293768278},
{"learn":[0.1606842752],"iteration":408,"passed_time":2.272385771,"remaining_time":3.283569659},
{"learn":[0.160530174],"iteration":409,"passed_time":2.290189636,"remaining_time":3.295638744},
{"learn":[0.1603504179],"iteration":410,"passed_time":2.306761619,"remaining_time":3.305797064},
{"learn":[0.1600673706],"iteration":411,"passed_time":2.321464802,"remaining_time":3.313158503},
{"learn":[0.160003562],"iteration":412,"passed_time":2.337077928,"remaining_time":3.321706402},
{"learn":[0.159860444],"iteration":413,"passed_time":2.339597985,"remaining_time":3.311604877},
{"learn":[0.159657447],"iteration":414,"passed_time":2.342084951,"remaining_time":3.301493245},
{"learn":[0.1595061024],"iteration":415,"passed_time":2.344768537,"remaining_time":3.291694292},
{"learn":[0.1593480928],"iteration":416,"passed_time":2.3470147,"remaining_time":3.281317914},
{"learn":[0.1592208801],"iteration":417,"passed_time":2.349469868,"remaining_time":3.271271443},
{"learn":[0.1591410389],"iteration":418,"passed_time":2.351804577,"remaining_time":3.261094175},
{"learn":[0.1588907206],"iteration":419,"passed_time":2.366470787,"remaining_time":3.267983467},
{"learn":[0.1586903991],"iteration":420,"passed_time":2.381411135,"remaining_time":3.27514738},
{"learn":[0.1584257046],"iteration":421,"passed_time":2.383777862,"remaining_time":3.264984844},
{"learn":[0.1583652507],"iteration":422,"passed_time":2.396026829,"remaining_time":3.268339197},
{"learn":[0.1583212642],"iteration":423,"passed_time":2.398471553,"remaining_time":3.258300977},
{"learn":[0.1582723536],"iteration":424,"passed_time":2.410619792,"remaining_time":3.261426778},
{"learn":[0.1581663928],"iteration":425,"passed_time":2.412625224,"remaining_time":3.250814269},
{"learn":[0.1578509777],"iteration":426,"passed_time":2.42606426,"remaining_time":3.255585061},
{"learn":[0.1577625804],"iteration":427,"passed_time":2.437521582,"remaining_time":3.257622301},
{"learn":[0.1575547563],"iteration":428,"passed_time":2.452160833,"remaining_time":3.263831785},
{"learn":[0.1574287822],"iteration":429,"passed_time":2.467966211,"remaining_time":3.271490094},
{"learn":[0.1573070091],"iteration":430,"passed_time":2.483908901,"remaining_time":3.279220799},
{"learn":[0.1569917982],"iteration":431,"passed_time":2.498977734,"remaining_time":3.285692947},
{"learn":[0.1567908956],"iteration":432,"passed_time":2.501701028,"remaining_time":3.275899499},
{"learn":[0.1565359771],"iteration":433,"passed_time":2.513963201,"remaining_time":3.278578737},
{"learn":[0.1563870477],"iteration":434,"passed_time":2.516350394,"remaining_time":3.268363156},
{"learn":[0.1562608194],"iteration":435,"passed_time":2.529997428,"remaining_time":3.272748966},
{"learn":[0.1560852511],"iteration":436,"passed_time":2.544892215,"remaining_time":3.278659765},
{"learn":[0.1559498385],"iteration":437,"passed_time":2.547306703,"remaining_time":3.268462025},
{"learn":[0.155758977],"iteration":438,"passed_time":2.549788218,"remaining_time":3.258385399},
{"learn":[0.1553832012],"iteration":439,"passed_time":2.552029862,"remaining_time":3.248038007},
{"learn":[0.1552532672],"iteration":440,"passed_time":2.554524769,"remaining_time":3.238048403},
{"learn":[0.1551210904],"iteration":441,"passed_time":2.556871823,"remaining_time":3.227906057},
{"learn":[0.1549868236],"iteration":442,"passed_time":2.559181889,"remaining_time":3.217752398},
{"learn":[0.154841993],"iteration":443,"passed_time":2.561847407,"remaining_time":3.208079186},
{"learn":[0.1546452643],"iteration":444,"passed_time":2.564468464,"remaining_time":3.198382017},
{"learn":[0.154465977],"iteration":445,"passed_time":2.567126841,"remaining_time":3.188762937},
{"learn":[0.1543408626],"iteration":446,"passed_time":2.575164572,"remaining_time":3.185829997},
{"learn":[0.1542182631],"iteration":447,"passed_time":2.577313523,"remaining_time":3.175618448},
{"learn":[0.1539499096],"iteration":448,"passed_time":2.579485389,"remaining_time":3.165470934},
{"learn":[0.1538296738],"iteration":449,"passed_time":2.581546115,"remaining_time":3.15522303},
{"learn":[0.1536823248],"iteration":450,"passed_time":2.583961585,"remaining_time":3.145443259},
{"learn":[0.1535447423],"iteration":451,"passed_time":2.586372014,"remaining_time":3.135689963},
{"learn":[0.1534251845],"iteration":452,"passed_time":2.588686178,"remaining_time":3.125852846},
{"learn":[0.1532085998],"iteration":453,"passed_time":2.605591907,"remaining_time":3.133597315},
{"learn":[0.1530425312],"iteration":454,"passed_time":2.608023694,"remaining_time":3.123896512},
{"learn":[0.1527818992],"iteration":455,"passed_time":2.610199071,"remaining_time":3.113921699},
{"learn":[0.1525135867],"iteration":456,"passed_time":2.612461823,"remaining_time":3.104084835},
{"learn":[0.1523586733],"iteration":457,"passed_time":2.614973238,"remaining_time":3.094575316},
{"learn":[0.1522385155],"iteration":458,"passed_time":2.617079544,"remaining_time":3.084618809},
{"learn":[0.1520075544],"iteration":459,"passed_time":2.619507217,"remaining_time":3.07507369},
{"learn":[0.1517616139],"iteration":460,"passed_time":2.621689504,"remaining_time":3.065272544},
{"learn":[0.1514703567],"iteration":461,"passed_time":2.624142653,"remaining_time":3.055819799},
{"learn":[0.15143192],"iteration":462,"passed_time":2.626545213,"remaining_time":3.046338617},
{"learn":[0.1512599808],"iteration":463,"passed_time":2.62889881,"remaining_time":3.036831384},
{"learn":[0.1510637778],"iteration":464,"passed_time":2.631364613,"remaining_time":3.027484017},
{"learn":[0.1509630762],"iteration":465,"passed_time":2.633570076,"remaining_time":3.017867855},
{"learn":[0.1508721866],"iteration":466,"passed_time":2.635776815,"remaining_time":3.008284888},
{"learn":[0.1507358255],"iteration":467,"passed_time":2.651767105,"remaining_time":3.014401923},
{"learn":[0.1506381677],"iteration":468,"passed_time":2.654193957,"remaining_time":3.005068212},
{"learn":[0.1505494238],"iteration":469,"passed_time":2.666281714,"remaining_time":3.006658103},
{"learn":[0.1503775455],"iteration":470,"passed_time":2.680956861,"remaining_time":3.011095922},
{"learn":[0.1502715182],"iteration":471,"passed_time":2.696672721,"remaining_time":3.016616942},
{"learn":[0.1501208812],"iteration":472,"passed_time":2.699716076,"remaining_time":3.007928905},
{"learn":[0.1500086484],"iteration":473,"passed_time":2.703355909,"remaining_time":2.999926599},
{"learn":[0.1498438133],"iteration":474,"passed_time":2.705735225,"remaining_time":2.990549459},
{"learn":[0.1497395094],"iteration":475,"passed_time":2.711241883,"remaining_time":2.984644426},
{"learn":[0.1495770537],"iteration":476,"passed_time":2.726967914,"remaining_time":2.989945952},
{"learn":[0.1494220714],"iteration":477,"passed_time":2.729709024,"remaining_time":2.980979311},
{"learn":[0.1493214163],"iteration":478,"passed_time":2.741757333,"remaining_time":2.982161942},
{"learn":[0.1492425074],"iteration":479,"passed_time":2.744368159,"remaining_time":2.973065506},
{"learn":[0.1490259034],"iteration":480,"passed_time":2.746827254,"remaining_time":2.963832318},
{"learn":[0.1488441543],"iteration":481,"passed_time":2.749256436,"remaining_time":2.954595091},
{"learn":[0.1485997119],"iteration":482,"passed_time":2.751757024,"remaining_time":2.945462487},
{"learn":[0.1484965138],"iteration":483,"passed_time":2.754090908,"remaining_time":2.936179563},
{"learn":[0.1483265614],"iteration":484,"passed_time":2.756885499,"remaining_time":2.927414499},
{"learn":[0.1481660908],"iteration":485,"passed_time":2.75963509,"remaining_time":2.918626412},
{"learn":[0.1478301429],"iteration":486,"passed_time":2.762337262,"remaining_time":2.909813173},
{"learn":[0.1476630864],"iteration":487,"passed_time":2.764745171,"remaining_time":2.900716245},
{"learn":[0.1475305788],"iteration":488,"passed_time":2.77180789,"remaining_time":2.896510904},
{"learn":[0.1473825874],"iteration":489,"passed_time":2.77421392,"remaining_time":2.887447142},
{"learn":[0.147237664],"iteration":490,"passed_time":2.786813472,"remaining_time":2.888977713},
{"learn":[0.1470514299],"iteration":491,"passed_time":2.789315393,"remaining_time":2.880024836},
{"learn":[0.1468599304],"iteration":492,"passed_time":2.79197978,"remaining_time":2.87126521},
{"learn":[0.1467124486],"iteration":493,"passed_time":2.801727337,"remaining_time":2.869785491},
{"learn":[0.1465485216],"iteration":494,"passed_time":2.804197565,"remaining_time":2.860848021},
{"learn":[0.14640872],"iteration":495,"passed_time":2.806573641,"remaining_time":2.851840957},
{"learn":[0.1461342051],"iteration":496,"passed_time":2.809183196,"remaining_time":2.843096876},
{"learn":[0.1460129703],"iteration":497,"passed_time":2.811329862,"remaining_time":2.833910825},
{"learn":[0.1459030151],"iteration":498,"passed_time":2.813460977,"remaining_time":2.824737374},
{"learn":[0.1457976355],"iteration":499,"passed_time":2.815849723,"remaining_time":2.815849723},
{"learn":[0.1456034606],"iteration":500,"passed_time":2.818305522,"remaining_time":2.807054801},
{"learn":[0.1454809425],"iteration":501,"passed_time":2.820967841,"remaining_time":2.79849001},
{"learn":[0.1453667826],"iteration":502,"passed_time":2.823308342,"remaining_time":2.789630707},
{"learn":[0.1451361884],"iteration":503,"passed_time":2.825788594,"remaining_time":2.780934807},
{"learn":[0.1450386224],"iteration":504,"passed_time":2.828188368,"remaining_time":2.772184638},
{"learn":[0.1448181037],"iteration":505,"passed_time":2.83035847,"remaining_time":2.763235345},
{"learn":[0.1445335932],"iteration":506,"passed_time":2.832830822,"remaining_time":2.754606697},
{"learn":[0.1444175419],"iteration":507,"passed_time":2.835118222,"remaining_time":2.74582316},
{"learn":[0.144284856],"iteration":508,"passed_time":2.837551202,"remaining_time":2.73720558},
{"learn":[0.1441100673],"iteration":509,"passed_time":2.840000588,"remaining_time":2.728628016},
{"learn":[0.1439181052],"iteration":510,"passed_time":2.842279877,"remaining_time":2.719911663},
{"learn":[0.1437145989],"iteration":511,"passed_time":2.844832273,"remaining_time":2.71148076},
{"learn":[0.1434955689],"iteration":512,"passed_time":2.847161867,"remaining_time":2.702861265},
{"learn":[0.1433395516],"iteration":513,"passed_time":2.849581635,"remaining_time":2.694351507},
{"learn":[0.1432219764],"iteration":514,"passed_time":2.852052454,"remaining_time":2.685913476},
{"learn":[0.1430358331],"iteration":515,"passed_time":2.854414758,"remaining_time":2.677396788},
{"learn":[0.1428928567],"iteration":516,"passed_time":2.856861705,"remaining_time":2.668982985},
{"learn":[0.1427700165],"iteration":517,"passed_time":2.859260711,"remaining_time":2.660547612},
{"learn":[0.1426717966],"iteration":518,"passed_time":2.861680178,"remaining_time":2.652154462},
{"learn":[0.1424812014],"iteration":519,"passed_time":2.864010168,"remaining_time":2.643701693},
{"learn":[0.142335335],"iteration":520,"passed_time":2.866318411,"remaining_time":2.635252436},
{"learn":[0.1421307026],"iteration":521,"passed_time":2.868634653,"remaining_time":2.626834031},
{"learn":[0.1419640075],"iteration":522,"passed_time":2.870764415,"remaining_time":2.618268884},
{"learn":[0.141781167],"iteration":523,"passed_time":2.873163704,"remaining_time":2.609973135},
{"learn":[0.1416541068],"iteration":524,"passed_time":2.875414024,"remaining_time":2.601565069},
{"learn":[0.1414932733],"iteration":525,"passed_time":2.878136923,"remaining_time":2.593606277},
{"learn":[0.141336557],"iteration":526,"passed_time":2.880607346,"remaining_time":2.585440749},
{"learn":[0.1412291656],"iteration":527,"passed_time":2.883239084,"remaining_time":2.577441},
{"learn":[0.141081668],"iteration":528,"passed_time":2.885821384,"remaining_time":2.569417527},
{"learn":[0.1409959817],"iteration":529,"passed_time":2.888136955,"remaining_time":2.561178055},
{"learn":[0.1409428367],"iteration":530,"passed_time":2.890536653,"remaining_time":2.553035198},
{"learn":[0.1408469464],"iteration":531,"passed_time":2.892893917,"remaining_time":2.544876604},
{"learn":[0.1406387159],"iteration":532,"passed_time":2.895051441,"remaining_time":2.536564771},
{"learn":[0.1404657001],"iteration":533,"passed_time":2.897597238,"remaining_time":2.528614818},
{"learn":[0.1403025472],"iteration":534,"passed_time":2.899714686,"remaining_time":2.520312765},
{"learn":[0.1401884843],"iteration":535,"passed_time":2.901969903,"remaining_time":2.51215305},
{"learn":[0.1400898723],"iteration":536,"passed_time":2.904521612,"remaining_time":2.504270961},
{"learn":[0.1399813234],"iteration":537,"passed_time":2.906924546,"remaining_time":2.49628093},
{"learn":[0.1398813922],"iteration":538,"passed_time":2.909468189,"remaining_time":2.488431976},
{"learn":[0.1397892231],"iteration":539,"passed_time":2.911933943,"remaining_time":2.480536322},
{"learn":[0.1396347648],"iteration":540,"passed_time":2.914660825,"remaining_time":2.47288229},
{"learn":[0.1395027625],"iteration":541,"passed_time":2.923427212,"remaining_time":2.470349931},
{"learn":[0.1393701677],"iteration":542,"passed_time":2.925894233,"remaining_time":2.462492936},
{"learn":[0.1392101444],"iteration":543,"passed_time":2.938477197,"remaining_time":2.463135298},
{"learn":[0.1391328706],"iteration":544,"passed_time":2.940737533,"remaining_time":2.455111152},
{"learn":[0.138995976],"iteration":545,"passed_time":2.943286833,"remaining_time":2.447348393},
{"learn":[0.1388669898],"iteration":546,"passed_time":2.953901199,"remaining_time":2.446283808},
{"learn":[0.1385689079],"iteration":547,"passed_time":2.956248703,"remaining_time":2.438365719},
{"learn":[0.138468828],"iteration":548,"passed_time":2.958418986,"remaining_time":2.430322337},
{"learn":[0.1382841382],"iteration":549,"passed_time":2.960865457,"remaining_time":2.422526283},
{"learn":[0.1381918365],"iteration":550,"passed_time":2.963128574,"remaining_time":2.414600236},
{"learn":[0.1379749097],"iteration":551,"passed_time":2.965277976,"remaining_time":2.406602415},
{"learn":[0.1378668598],"iteration":552,"passed_time":2.967630616,"remaining_time":2.398790028},
{"learn":[0.1377729684],"iteration":553,"passed_time":2.969794668,"remaining_time":2.390845527},
{"learn":[0.13768432],"iteration":554,"passed_time":2.972040621,"remaining_time":2.382987525},
{"learn":[0.1374553778],"iteration":555,"passed_time":2.974450302,"remaining_time":2.375280457},
{"learn":[0.1373354689],"iteration":556,"passed_time":2.983986356,"remaining_time":2.373260244},
{"learn":[0.1372572886],"iteration":557,"passed_time":2.986719565,"remaining_time":2.365824458},
{"learn":[0.1371644878],"iteration":558,"passed_time":2.988872995,"remaining_time":2.357948105},
{"learn":[0.1369465378],"iteration":559,"passed_time":2.991399083,"remaining_time":2.350384994},
{"learn":[0.1368378765],"iteration":560,"passed_time":2.993698983,"remaining_time":2.342662841},
{"learn":[0.1366263982],"iteration":561,"passed_time":2.996172312,"remaining_time":2.335095147},
{"learn":[0.1364768998],"iteration":562,"passed_time":2.998434407,"remaining_time":2.327381591},
{"learn":[0.1363844446],"iteration":563,"passed_time":3.00057157,"remaining_time":2.319590788},
{"learn":[0.1360840037],"iteration":564,"passed_time":3.003113534,"remaining_time":2.312131659},
{"learn":[0.1359818185],"iteration":565,"passed_time":3.005256353,"remaining_time":2.304383847},
{"learn":[0.1358395469],"iteration":566,"passed_time":3.007514916,"remaining_time":2.296744195},
{"learn":[0.1357263291],"iteration":567,"passed_time":3.010080488,"remaining_time":2.289356991},
{"learn":[0.1355934651],"iteration":568,"passed_time":3.012506308,"remaining_time":2.281880877},
{"learn":[0.1355000769],"iteration":569,"passed_time":3.014765437,"remaining_time":2.274296734},
{"learn":[0.1353369605],"iteration":570,"passed_time":3.017090447,"remaining_time":2.266780739},
{"learn":[0.1351323071],"iteration":571,"passed_time":3.019408087,"remaining_time":2.25927738},
{"learn":[0.1350128615],"iteration":572,"passed_time":3.021824123,"remaining_time":2.251865446},
{"learn":[0.1348185436],"iteration":573,"passed_time":3.023987192,"remaining_time":2.244283177},
{"learn":[0.1345869859],"iteration":574,"passed_time":3.026419068,"remaining_time":2.236918442},
{"learn":[0.134501529],"iteration":575,"passed_time":3.028696068,"remaining_time":2.229456828},
{"learn":[0.1343803399],"iteration":576,"passed_time":3.030920203,"remaining_time":2.221974429},
{"learn":[0.1342240266],"iteration":577,"passed_time":3.04307367,"remaining_time":2.221759669},
{"learn":[0.1340530719],"iteration":578,"passed_time":3.058292405,"remaining_time":2.223732474},
{"learn":[0.1337744384],"iteration":579,"passed_time":3.060543668,"remaining_time":2.21625576},
{"learn":[0.1336586665],"iteration":580,"passed_time":3.073587466,"remaining_time":2.21658029},
{"learn":[0.13351932],"iteration":581,"passed_time":3.075755475,"remaining_time":2.209047747},
{"learn":[0.1333958074],"iteration":582,"passed_time":3.078030796,"remaining_time":2.201610364},
{"learn":[0.1332292242],"iteration":583,"passed_time":3.080804009,"remaining_time":2.194545322},
{"learn":[0.1330154939],"iteration":584,"passed_time":3.083009648,"remaining_time":2.187092314},
{"learn":[0.1327111602],"iteration":585,"passed_time":3.085316757,"remaining_time":2.179728903},
{"learn":[0.1325367293],"iteration":586,"passed_time":3.087685674,"remaining_time":2.172426207},
{"learn":[0.1323215765],"iteration":587,"passed_time":3.104961467,"remaining_time":2.175585246},
{"learn":[0.13222871],"iteration":588,"passed_time":3.119845233,"remaining_time":2.177005757},
{"learn":[0.1321368303],"iteration":589,"passed_time":3.122398686,"remaining_time":2.169802477},
{"learn":[0.1319419268],"iteration":590,"passed_time":3.134796051,"remaining_time":2.169427386},
{"learn":[0.1318506908],"iteration":591,"passed_time":3.150452194,"remaining_time":2.171257593},
{"learn":[0.1317125251],"iteration":592,"passed_time":3.165114896,"remaining_time":2.172346986},
{"learn":[0.1314471383],"iteration":593,"passed_time":3.167337222,"remaining_time":2.164880324},
{"learn":[0.1312129706],"iteration":594,"passed_time":3.170239672,"remaining_time":2.15789423},
{"learn":[0.1310175981],"iteration":595,"passed_time":3.180532009,"remaining_time":2.155931093},
{"learn":[0.1309556056],"iteration":596,"passed_time":3.183051589,"remaining_time":2.148693116},
{"learn":[0.1307704052],"iteration":597,"passed_time":3.185378298,"remaining_time":2.141341264},
{"learn":[0.1307021133],"iteration":598,"passed_time":3.187989545,"remaining_time":2.134196674},
{"learn":[0.1304702548],"iteration":599,"passed_time":3.190539752,"remaining_time":2.127026501},
{"learn":[0.1303076819],"iteration":600,"passed_time":3.192945692,"remaining_time":2.119775925},
{"learn":[0.1303036458],"iteration":601,"passed_time":3.194168016,"remaining_time":2.111758921},
{"learn":[0.1301408192],"iteration":602,"passed_time":3.196652191,"remaining_time":2.104595224},
{"learn":[0.1299641192],"iteration":603,"passed_time":3.199220704,"remaining_time":2.097502316},
{"learn":[0.1298418463],"iteration":604,"passed_time":3.201448601,"remaining_time":2.090201979},
{"learn":[0.1295390144],"iteration":605,"passed_time":3.204008342,"remaining_time":2.083134136},
{"learn":[0.129439201],"iteration":606,"passed_time":3.20654224,"remaining_time":2.076064416},
{"learn":[0.1291880573],"iteration":607,"passed_time":3.209059357,"remaining_time":2.068998796},
{"learn":[0.1290946041],"iteration":608,"passed_time":3.211726119,"remaining_time":2.062044191},
{"learn":[0.1289598338],"iteration":609,"passed_time":3.214057848,"remaining_time":2.054889444},
{"learn":[0.1288050842],"iteration":610,"passed_time":3.216636775,"remaining_time":2.047907865},
{"learn":[0.1286828918],"iteration":611,"passed_time":3.218980492,"remaining_time":2.040791554},
{"learn":[0.1285769982],"iteration":612,"passed_time":3.221232397,"remaining_time":2.033632851},
{"learn":[0.1284632553],"iteration":613,"passed_time":3.223645462,"remaining_time":2.026591447},
{"learn":[0.1282450194],"iteration":614,"passed_time":3.225931755,"remaining_time":2.019485733},
{"learn":[0.1281055962],"iteration":615,"passed_time":3.228527031,"remaining_time":2.012588279},
{"learn":[0.1278868513],"iteration":616,"passed_time":3.230722249,"remaining_time":2.005456437},
{"learn":[0.127696922],"iteration":617,"passed_time":3.233239681,"remaining_time":1.998539738},
{"learn":[0.1275882705],"iteration":618,"passed_time":3.235765162,"remaining_time":1.991642208},
{"learn":[0.1274838546],"iteration":619,"passed_time":3.238301285,"remaining_time":1.984765304},
{"learn":[0.1272972328],"iteration":620,"passed_time":3.24081021,"remaining_time":1.97788578},
{"learn":[0.127154537],"iteration":621,"passed_time":3.243174322,"remaining_time":1.970932305},
{"learn":[0.1270236956],"iteration":622,"passed_time":3.245573233,"remaining_time":1.964014621},
{"learn":[0.1268823049],"iteration":623,"passed_time":3.25370136,"remaining_time":1.96056364},
{"learn":[0.1267287332],"iteration":624,"passed_time":3.256165325,"remaining_time":1.953699195},
{"learn":[0.1265873322],"iteration":625,"passed_time":3.269686344,"remaining_time":1.95345478},
{"learn":[0.1263425697],"iteration":626,"passed_time":3.272049159,"remaining_time":1.946530042},
{"learn":[0.126125701],"iteration":627,"passed_time":3.284670343,"remaining_time":1.945696445},
{"learn":[0.1259548159],"iteration":628,"passed_time":3.287468662,"remaining_time":1.939031595},
{"learn":[0.1259278759],"iteration":629,"passed_time":3.289733047,"remaining_time":1.93206544},
{"learn":[0.1257996449],"iteration":630,"passed_time":3.292007817,"remaining_time":1.925120261},
{"learn":[0.1256089453],"iteration":631,"passed_time":3.294360707,"remaining_time":1.918235348},
{"learn":[0.1254093372],"iteration":632,"passed_time":3.296789673,"remaining_time":1.911408863},
{"learn":[0.1252642216],"iteration":633,"passed_time":3.299451376,"remaining_time":1.904730605},
{"learn":[0.1250249478],"iteration":634,"passed_time":3.301679474,"remaining_time":1.897815761},
{"learn":[0.124975303],"iteration":635,"passed_time":3.304081325,"remaining_time":1.891015098},
{"learn":[0.1248299115],"iteration":636,"passed_time":3.315975573,"remaining_time":1.889637572},
{"learn":[0.1247234723],"iteration":637,"passed_time":3.318373458,"remaining_time":1.882838858},
{"learn":[0.1245988479],"iteration":638,"passed_time":3.320648619,"remaining_time":1.875984587},
{"learn":[0.1244164368],"iteration":639,"passed_time":3.322900774,"remaining_time":1.869131686},
{"learn":[0.1242442473],"iteration":640,"passed_time":3.325231334,"remaining_time":1.86233705},
{"learn":[0.1240748371],"iteration":641,"passed_time":3.327680882,"remaining_time":1.855622672},
{"learn":[0.1238983777],"iteration":642,"passed_time":3.330085234,"remaining_time":1.848896468},
{"learn":[0.1238215888],"iteration":643,"passed_time":3.332566409,"remaining_time":1.842226151},
{"learn":[0.1237571081],"iteration":644,"passed_time":3.335121144,"remaining_time":1.835609312},
{"learn":[0.1236987125],"iteration":645,"passed_time":3.346003728,"remaining_time":1.833568606},
{"learn":[0.1235897921],"iteration":646,"passed_time":3.348545872,"remaining_time":1.826950066},
{"learn":[0.1234074304],"iteration":647,"passed_time":3.361622269,"remaining_time":1.826066418},
{"learn":[0.1232493335],"iteration":648,"passed_time":3.364561316,"remaining_time":1.819662592},
{"learn":[0.1230641171],"iteration":649,"passed_time":3.367000392,"remaining_time":1.813000211},
{"learn":[0.1229716732],"iteration":650,"passed_time":3.369424639,"remaining_time":1.806342856},
{"learn":[0.1228936713],"iteration":651,"passed_time":3.371892468,"remaining_time":1.799721747},
{"learn":[0.1227526938],"iteration":652,"passed_time":3.374340967,"remaining_time":1.793103086},
{"learn":[0.1226416464],"iteration":653,"passed_time":3.391660206,"remaining_time":1.794364574},
{"learn":[0.1224930089],"iteration":654,"passed_time":3.406941014,"remaining_time":1.794495649},
{"learn":[0.1224327531],"iteration":655,"passed_time":3.421556212,"remaining_time":1.794230697},
{"learn":[0.1223535132],"iteration":656,"passed_time":3.424003815,"remaining_time":1.787569724},
{"learn":[0.1222858527],"iteration":657,"passed_time":3.437123224,"remaining_time":1.786468302},
{"learn":[0.1221413837],"iteration":658,"passed_time":3.454453499,"remaining_time":1.787509322},
{"learn":[0.1220396335],"iteration":659,"passed_time":3.467856203,"remaining_time":1.786471377},
{"learn":[0.1218848294],"iteration":660,"passed_time":3.470536107,"remaining_time":1.779896733},
{"learn":[0.1216498368],"iteration":661,"passed_time":3.473245292,"remaining_time":1.773348805},
{"learn":[0.1214919129],"iteration":662,"passed_time":3.484091196,"remaining_time":1.770948316},
{"learn":[0.1214064347],"iteration":663,"passed_time":3.500048286,"remaining_time":1.771108771},
{"learn":[0.1213081303],"iteration":664,"passed_time":3.515470524,"remaining_time":1.770951317},
{"learn":[0.1211996471],"iteration":665,"passed_time":3.531444997,"remaining_time":1.771024968},
{"learn":[0.1211371697],"iteration":666,"passed_time":3.546167843,"remaining_time":1.770425625},
{"learn":[0.1209454051],"iteration":667,"passed_time":3.548542121,"remaining_time":1.763646683},
{"learn":[0.1208040843],"iteration":668,"passed_time":3.562936603,"remaining_time":1.762828125},
{"learn":[0.120675914],"iteration":669,"passed_time":3.565476232,"remaining_time":1.756130084},
{"learn":[0.1205087136],"iteration":670,"passed_time":3.577237391,"remaining_time":1.753965875},
{"learn":[0.1204454426],"iteration":671,"passed_time":3.59258934,"remaining_time":1.753525749},
{"learn":[0.1203606734],"iteration":672,"passed_time":3.608224776,"remaining_time":1.753179052},
{"learn":[0.1202919872],"iteration":673,"passed_time":3.623495785,"remaining_time":1.752610721},
{"learn":[0.1201304299],"iteration":674,"passed_time":3.626192427,"remaining_time":1.745944502},
{"learn":[0.1200511591],"iteration":675,"passed_time":3.638236417,"remaining_time":1.743770117},
{"learn":[0.1199702945],"iteration":676,"passed_time":3.641099143,"remaining_time":1.737186149},
{"learn":[0.1199487062],"iteration":677,"passed_time":3.64337737,"remaining_time":1.730335565},
{"learn":[0.1198733185],"iteration":678,"passed_time":3.645717931,"remaining_time":1.723527917},
{"learn":[0.1197516049],"iteration":679,"passed_time":3.648069263,"remaining_time":1.716738477},
{"learn":[0.1196026775],"iteration":680,"passed_time":3.650441406,"remaining_time":1.709971819},
{"learn":[0.1194507465],"iteration":681,"passed_time":3.668525893,"remaining_time":1.710544331},
{"learn":[0.1193712464],"iteration":682,"passed_time":3.684327995,"remaining_time":1.710002891},
{"learn":[0.1191571806],"iteration":683,"passed_time":3.699171054,"remaining_time":1.708973762},
{"learn":[0.118995465],"iteration":684,"passed_time":3.714463827,"remaining_time":1.708111103},
{"learn":[0.1188616322],"iteration":685,"passed_time":3.730391848,"remaining_time":1.707497143},
{"learn":[0.1187497484],"iteration":686,"passed_time":3.746722006,"remaining_time":1.707021816},
{"learn":[0.1186056769],"iteration":687,"passed_time":3.749604331,"remaining_time":1.700401964},
{"learn":[0.1184290753],"iteration":688,"passed_time":3.752027516,"remaining_time":1.693585715},
{"learn":[0.118358586],"iteration":689,"passed_time":3.754542723,"remaining_time":1.686823542},
{"learn":[0.1182303084],"iteration":690,"passed_time":3.761900962,"remaining_time":1.682239359},
{"learn":[0.1181203055],"iteration":691,"passed_time":3.764417357,"remaining_time":1.675492118},
{"learn":[0.1179755976],"iteration":692,"passed_time":3.766608231,"remaining_time":1.668612881},
{"learn":[0.1177977217],"iteration":693,"passed_time":3.769050768,"remaining_time":1.66185812},
{"learn":[0.1176508264],"iteration":694,"passed_time":3.771360473,"remaining_time":1.655057474},
{"learn":[0.1175448096],"iteration":695,"passed_time":3.773585795,"remaining_time":1.648232876},
{"learn":[0.1174261025],"iteration":696,"passed_time":3.775959211,"remaining_time":1.641485855},
{"learn":[0.1172539546],"iteration":697,"passed_time":3.778260644,"remaining_time":1.634720221},
{"learn":[0.1171191692],"iteration":698,"passed_time":3.780462119,"remaining_time":1.627924317},
{"learn":[0.1170790195],"iteration":699,"passed_time":3.782804373,"remaining_time":1.621201874},
{"learn":[0.1168242064],"iteration":700,"passed_time":3.785326799,"remaining_time":1.614568777},
{"learn":[0.1166870345],"iteration":701,"passed_time":3.788036717,"remaining_time":1.608026982},
{"learn":[0.1166159758],"iteration":702,"passed_time":3.790697493,"remaining_time":1.601475328},
{"learn":[0.1165280352],"iteration":703,"passed_time":3.793381795,"remaining_time":1.594944618},
{"learn":[0.1163956149],"iteration":704,"passed_time":3.807045642,"remaining_time":1.593019098},
{"learn":[0.1162863315],"iteration":705,"passed_time":3.82275041,"remaining_time":1.591910227},
{"learn":[0.1162203939],"iteration":706,"passed_time":3.838333673,"remaining_time":1.590709712},
{"learn":[0.1161202783],"iteration":707,"passed_time":3.840744448,"remaining_time":1.584035846},
{"learn":[0.1159988715],"iteration":708,"passed_time":3.853278685,"remaining_time":1.581529051},
{"learn":[0.1159178374],"iteration":709,"passed_time":3.868360964,"remaining_time":1.58003476},
{"learn":[0.1157406078],"iteration":710,"passed_time":3.870661315,"remaining_time":1.573306779},
{"learn":[0.1156033713],"iteration":711,"passed_time":3.872898962,"remaining_time":1.566565872},
{"learn":[0.1154829216],"iteration":712,"passed_time":3.874987172,"remaining_time":1.559777445},
{"learn":[0.1152969516],"iteration":713,"passed_time":3.877820365,"remaining_time":1.553300594},
{"learn":[0.1151579557],"iteration":714,"passed_time":3.884686869,"remaining_time":1.548441619},
{"learn":[0.1150134873],"iteration":715,"passed_time":3.888219013,"remaining_time":1.542254469},
{"learn":[0.1148856623],"iteration":716,"passed_time":3.899759875,"remaining_time":1.539235767},
{"learn":[0.1147293129],"iteration":717,"passed_time":3.91567168,"remaining_time":1.537910047},
{"learn":[0.1145893746],"iteration":718,"passed_time":3.918315946,"remaining_time":1.531358527},
{"learn":[0.1144947789],"iteration":719,"passed_time":3.930374982,"remaining_time":1.52847916},
{"learn":[0.1143745638],"iteration":720,"passed_time":3.932865174,"remaining_time":1.521871545},
{"learn":[0.1143215763],"iteration":721,"passed_time":3.935251676,"remaining_time":1.51523541},
{"learn":[0.1142311249],"iteration":722,"passed_time":3.9379013,"remaining_time":1.50871184},
{"learn":[0.1140967614],"iteration":723,"passed_time":3.940354434,"remaining_time":1.502124066},
{"learn":[0.1140416339],"iteration":724,"passed_time":3.942824712,"remaining_time":1.495554201},
{"learn":[0.1139114793],"iteration":725,"passed_time":3.945605294,"remaining_time":1.489112742},
{"learn":[0.1138313687],"iteration":726,"passed_time":3.961692612,"remaining_time":1.487678243},
{"learn":[0.113705135],"iteration":727,"passed_time":3.976912218,"remaining_time":1.48587929},
{"learn":[0.1135981456],"iteration":728,"passed_time":3.992075312,"remaining_time":1.48402251},
{"learn":[0.1135032641],"iteration":729,"passed_time":3.994519799,"remaining_time":1.477425131},
{"learn":[0.1133997444],"iteration":730,"passed_time":3.996999796,"remaining_time":1.470852182},
{"learn":[0.1132780879],"iteration":731,"passed_time":3.999208305,"remaining_time":1.464191019},
{"learn":[0.113134454],"iteration":732,"passed_time":4.001832368,"remaining_time":1.457693373},
{"learn":[0.113043656],"iteration":733,"passed_time":4.00443342,"remaining_time":1.451197943},
{"learn":[0.1129213618],"iteration":734,"passed_time":4.006771416,"remaining_time":1.444618266},
{"learn":[0.1127294746],"iteration":735,"passed_time":4.009120173,"remaining_time":1.438053975},
{"learn":[0.1124849154],"iteration":736,"passed_time":4.011414728,"remaining_time":1.431481782},
{"learn":[0.1123532226],"iteration":737,"passed_time":4.013722674,"remaining_time":1.424925936},
{"learn":[0.1122413659],"iteration":738,"passed_time":4.01615196,"remaining_time":1.418424441},
{"learn":[0.1121479237],"iteration":739,"passed_time":4.018546538,"remaining_time":1.411921757},
{"learn":[0.1120501383],"iteration":740,"passed_time":4.021443292,"remaining_time":1.405605685},
{"learn":[0.1119398919],"iteration":741,"passed_time":4.023952046,"remaining_time":1.399163919},
{"learn":[0.1117332039],"iteration":742,"passed_time":4.026380597,"remaining_time":1.392704998},
{"learn":[0.1116428342],"iteration":743,"passed_time":4.028557222,"remaining_time":1.386170227},
{"learn":[0.1116013433],"iteration":744,"passed_time":4.030834599,"remaining_time":1.379681641},
{"learn":[0.1115090168],"iteration":745,"passed_time":4.033383305,"remaining_time":1.373296729},
{"learn":[0.1114145331],"iteration":746,"passed_time":4.035784201,"remaining_time":1.366872025},
{"learn":[0.1113257831],"iteration":747,"passed_time":4.038350421,"remaining_time":1.360513778},
{"learn":[0.111253403],"iteration":748,"passed_time":4.04063773,"remaining_time":1.35407219},
{"learn":[0.1111342488],"iteration":749,"passed_time":4.043216122,"remaining_time":1.347738707},
{"learn":[0.1110449631],"iteration":750,"passed_time":4.045748963,"remaining_time":1.341400122},
{"learn":[0.1109767275],"iteration":751,"passed_time":4.048226606,"remaining_time":1.335053455},
{"learn":[0.1107887701],"iteration":752,"passed_time":4.052553655,"remaining_time":1.329323709},
{"learn":[0.1106304032],"iteration":753,"passed_time":4.065824628,"remaining_time":1.326515727},
{"learn":[0.1105106864],"iteration":754,"passed_time":4.080801629,"remaining_time":1.324233641},
{"learn":[0.1103754618],"iteration":755,"passed_time":4.083405944,"remaining_time":1.31792467},
{"learn":[0.1102946838],"iteration":756,"passed_time":4.085897899,"remaining_time":1.311589418},
{"learn":[0.1101650089],"iteration":757,"passed_time":4.088334104,"remaining_time":1.305246508},
{"learn":[0.1100921817],"iteration":758,"passed_time":4.090719789,"remaining_time":1.298897851},
{"learn":[0.1099879491],"iteration":759,"passed_time":4.095660745,"remaining_time":1.293366551},
{"learn":[0.1098747099],"iteration":760,"passed_time":4.097986963,"remaining_time":1.287015617},
{"learn":[0.109805969],"iteration":761,"passed_time":4.100349883,"remaining_time":1.280686709},
{"learn":[0.1096712035],"iteration":762,"passed_time":4.102885697,"remaining_time":1.274421901},
{"learn":[0.1095705698],"iteration":763,"passed_time":4.105286237,"remaining_time":1.268125068},
{"learn":[0.1094404061],"iteration":764,"passed_time":4.107645238,"remaining_time":1.261825661},
{"learn":[0.1093508657],"iteration":765,"passed_time":4.110530358,"remaining_time":1.255697264},
{"learn":[0.1091704066],"iteration":766,"passed_time":4.112876326,"remaining_time":1.249413538},
{"learn":[0.1089615537],"iteration":767,"passed_time":4.115544119,"remaining_time":1.243237286},
{"learn":[0.1088482536],"iteration":768,"passed_time":4.117914709,"remaining_time":1.236980881},
{"learn":[0.1087509572],"iteration":769,"passed_time":4.120592719,"remaining_time":1.230826397},
{"learn":[0.1086123806],"iteration":770,"passed_time":4.124749561,"remaining_time":1.225120168},
{"learn":[0.1084626567],"iteration":771,"passed_time":4.127221202,"remaining_time":1.218920251},
{"learn":[0.1083837167],"iteration":772,"passed_time":4.129405969,"remaining_time":1.212645737},
{"learn":[0.1081710518],"iteration":773,"passed_time":4.131836763,"remaining_time":1.206453629},
{"learn":[0.1081040954],"iteration":774,"passed_time":4.1340694,"remaining_time":1.200213697},
{"learn":[0.1079616392],"iteration":775,"passed_time":4.136320058,"remaining_time":1.193989295},
{"learn":[0.1078615245],"iteration":776,"passed_time":4.138762622,"remaining_time":1.187830199},
{"learn":[0.1078011412],"iteration":777,"passed_time":4.141180078,"remaining_time":1.181673493},
{"learn":[0.1077330372],"iteration":778,"passed_time":4.14379329,"remaining_time":1.175581922},
{"learn":[0.1076188814],"iteration":779,"passed_time":4.154951891,"remaining_time":1.171909508},
{"learn":[0.1074798256],"iteration":780,"passed_time":4.170888338,"remaining_time":1.169557677},
{"learn":[0.1073719433],"iteration":781,"passed_time":4.186067649,"remaining_time":1.166960035},
{"learn":[0.1072913169],"iteration":782,"passed_time":4.200748778,"remaining_time":1.16419219},
{"learn":[0.1072087953],"iteration":783,"passed_time":4.203185349,"remaining_time":1.158020453},
{"learn":[0.1071274255],"iteration":784,"passed_time":4.205608553,"remaining_time":1.151854572},
{"learn":[0.1070418107],"iteration":785,"passed_time":4.216845149,"remaining_time":1.148097789},
{"learn":[0.1069456807],"iteration":786,"passed_time":4.219601844,"remaining_time":1.142026928},
{"learn":[0.1068498525],"iteration":787,"passed_time":4.222011035,"remaining_time":1.135870989},
{"learn":[0.1066892985],"iteration":788,"passed_time":4.231793511,"remaining_time":1.131696364},
{"learn":[0.1065989228],"iteration":789,"passed_time":4.234217387,"remaining_time":1.125551457},
{"learn":[0.1064502643],"iteration":790,"passed_time":4.236735259,"remaining_time":1.119440795},
{"learn":[0.106328362],"iteration":791,"passed_time":4.239511654,"remaining_time":1.113407101},
{"learn":[0.1060841909],"iteration":792,"passed_time":4.242258576,"remaining_time":1.107373928},
{"learn":[0.1059702504],"iteration":793,"passed_time":4.244835495,"remaining_time":1.101304927},
{"learn":[0.1058856081],"iteration":794,"passed_time":4.24757685,"remaining_time":1.095287112},
{"learn":[0.1057726084],"iteration":795,"passed_time":4.249952867,"remaining_time":1.089183901},
{"learn":[0.1056518538],"iteration":796,"passed_time":4.26134299,"remaining_time":1.085385981},
{"learn":[0.1055295747],"iteration":797,"passed_time":4.27708626,"remaining_time":1.082670958},
{"learn":[0.105348024],"iteration":798,"passed_time":4.28033688,"remaining_time":1.076780617},
{"learn":[0.1052677653],"iteration":799,"passed_time":4.283375069,"remaining_time":1.070843767},
{"learn":[0.1052024937],"iteration":800,"passed_time":4.291664069,"remaining_time":1.066218664},
{"learn":[0.1049942838],"iteration":801,"passed_time":4.30670934,"remaining_time":1.063252431},
{"learn":[0.1048169114],"iteration":802,"passed_time":4.309412105,"remaining_time":1.057228126},
{"learn":[0.1047503514],"iteration":803,"passed_time":4.322738893,"remaining_time":1.053802019},
{"learn":[0.1046518119],"iteration":804,"passed_time":4.338244506,"remaining_time":1.050879104},
{"learn":[0.1044542676],"iteration":805,"passed_time":4.354047419,"remaining_time":1.047996525},
{"learn":[0.1043630719],"iteration":806,"passed_time":4.356625401,"remaining_time":1.041919086},
{"learn":[0.1042185464],"iteration":807,"passed_time":4.359108264,"remaining_time":1.035827706},
{"learn":[0.1041038356],"iteration":808,"passed_time":4.369219672,"remaining_time":1.031546301},
{"learn":[0.1039970855],"iteration":809,"passed_time":4.371960563,"remaining_time":1.025521614},
{"learn":[0.10389114],"iteration":810,"passed_time":4.384714455,"remaining_time":1.02183851},
{"learn":[0.1037581286],"iteration":811,"passed_time":4.387208073,"remaining_time":1.015757534},
{"learn":[0.1036208348],"iteration":812,"passed_time":4.399960498,"remaining_time":1.012045035},
{"learn":[0.1035599169],"iteration":813,"passed_time":4.402441812,"remaining_time":1.005963363},
{"learn":[0.1035102874],"iteration":814,"passed_time":4.405076136,"remaining_time":0.9999252579},
{"learn":[0.1034216339],"iteration":815,"passed_time":4.407951387,"remaining_time":0.9939498226},
{"learn":[0.1033384552],"iteration":816,"passed_time":4.414987859,"remaining_time":0.9889140491},
{"learn":[0.1032988867],"iteration":817,"passed_time":4.430523356,"remaining_time":0.9857643653},
{"learn":[0.1032195401],"iteration":818,"passed_time":4.433469042,"remaining_time":0.9798020715},
{"learn":[0.1031147308],"iteration":819,"passed_time":4.43714229,"remaining_time":0.9740068441},
{"learn":[0.1030008874],"iteration":820,"passed_time":4.444595162,"remaining_time":0.9690408453},
{"learn":[0.1029167802],"iteration":821,"passed_time":4.448013911,"remaining_time":0.9631952264},
{"learn":[0.1028735624],"iteration":822,"passed_time":4.450556762,"remaining_time":0.9571671287},
{"learn":[0.1027728465],"iteration":823,"passed_time":4.453371042,"remaining_time":0.9512054654},
{"learn":[0.102654736],"iteration":824,"passed_time":4.455890979,"remaining_time":0.9451889955},
{"learn":[0.1025901895],"iteration":825,"passed_time":4.458477728,"remaining_time":0.9391950662},
{"learn":[0.1024693828],"iteration":826,"passed_time":4.461061115,"remaining_time":0.9332086734},
{"learn":[0.1023778913],"iteration":827,"passed_time":4.463582424,"remaining_time":0.927217605},
{"learn":[0.1022887235],"iteration":828,"passed_time":4.474177331,"remaining_time":0.9229002696},
{"learn":[0.1022084687],"iteration":829,"passed_time":4.476528773,"remaining_time":0.9168793872},
{"learn":[0.1020669099],"iteration":830,"passed_time":4.478903341,"remaining_time":0.9108720393},
{"learn":[0.1019036805],"iteration":831,"passed_time":4.481644166,"remaining_time":0.9049473796},
{"learn":[0.1018123824],"iteration":832,"passed_time":4.488649235,"remaining_time":0.8998852608},
{"learn":[0.1017058265],"iteration":833,"passed_time":4.49092146,"remaining_time":0.8938764537},
{"learn":[0.1016541526],"iteration":834,"passed_time":4.50451846,"remaining_time":0.8901144262},
{"learn":[0.1015872361],"iteration":835,"passed_time":4.507335866,"remaining_time":0.8842142129},
{"learn":[0.1015162125],"iteration":836,"passed_time":4.509661827,"remaining_time":0.8782256605},
{"learn":[0.1014636686],"iteration":837,"passed_time":4.512228302,"remaining_time":0.8722923448},
{"learn":[0.1013264517],"iteration":838,"passed_time":4.514652753,"remaining_time":0.8663398013},
{"learn":[0.1012657322],"iteration":839,"passed_time":4.516807872,"remaining_time":0.8603443565},
{"learn":[0.1010309375],"iteration":840,"passed_time":4.519543936,"remaining_time":0.8544678786},
{"learn":[0.1009628041],"iteration":841,"passed_time":4.521852424,"remaining_time":0.8485186258},
{"learn":[0.1008200425],"iteration":842,"passed_time":4.524371207,"remaining_time":0.8426171762},
{"learn":[0.1007439008],"iteration":843,"passed_time":4.535898779,"remaining_time":0.8383888738},
{"learn":[0.1006240525],"iteration":844,"passed_time":4.538503558,"remaining_time":0.8325065699},
{"learn":[0.1005617088],"iteration":845,"passed_time":4.541422952,"remaining_time":0.8266892843},
{"learn":[0.1005069255],"iteration":846,"passed_time":4.544210008,"remaining_time":0.8208549364},
{"learn":[0.1004146852],"iteration":847,"passed_time":4.550767489,"remaining_time":0.8157036066},
{"learn":[0.1003882346],"iteration":848,"passed_time":4.553095756,"remaining_time":0.8097967716},
{"learn":[0.1002866877],"iteration":849,"passed_time":4.555395485,"remaining_time":0.803893321},
{"learn":[0.1002593807],"iteration":850,"passed_time":4.557500229,"remaining_time":0.7979641998},
{"learn":[0.1001529309],"iteration":851,"passed_time":4.559883534,"remaining_time":0.7920924449},
{"learn":[0.1000282008],"iteration":852,"passed_time":4.562429372,"remaining_time":0.7862568788},
{"learn":[0.09982555598],"iteration":853,"passed_time":4.565010219,"remaining_time":0.7804350023},
{"learn":[0.09974090933],"iteration":854,"passed_time":4.567667778,"remaining_time":0.7746337168},
{"learn":[0.09966824814],"iteration":855,"passed_time":4.570350788,"remaining_time":0.7688440578},
{"learn":[0.09947530684],"iteration":856,"passed_time":4.57302269,"remaining_time":0.7630597955},
{"learn":[0.09939668325],"iteration":857,"passed_time":4.575246289,"remaining_time":0.7572085933},
{"learn":[0.09930303122],"iteration":858,"passed_time":4.577703902,"remaining_time":0.7514042493},
{"learn":[0.09919921067],"iteration":859,"passed_time":4.579958678,"remaining_time":0.7455746685},
{"learn":[0.09914331329],"iteration":860,"passed_time":4.596364536,"remaining_time":0.7420379449},
{"learn":[0.09909139104],"iteration":861,"passed_time":4.598848712,"remaining_time":0.7362426013},
{"learn":[0.09904018207],"iteration":862,"passed_time":4.601493311,"remaining_time":0.7304803981},
{"learn":[0.09894651318],"iteration":863,"passed_time":4.60387317,"remaining_time":0.7246837398},
{"learn":[0.09878849803],"iteration":864,"passed_time":4.610870394,"remaining_time":0.7196156106},
{"learn":[0.09870954417],"iteration":865,"passed_time":4.613446185,"remaining_time":0.7138588785},
{"learn":[0.09856724549],"iteration":866,"passed_time":4.616001371,"remaining_time":0.7081063234},
{"learn":[0.09845258131],"iteration":867,"passed_time":4.61854504,"remaining_time":0.702359384},
{"learn":[0.09832372185],"iteration":868,"passed_time":4.621081323,"remaining_time":0.6966187035},
{"learn":[0.0982085113],"iteration":869,"passed_time":4.623562773,"remaining_time":0.690877196},
{"learn":[0.09813010186],"iteration":870,"passed_time":4.626272982,"remaining_time":0.6851770547},
{"learn":[0.09800349081],"iteration":871,"passed_time":4.628847056,"remaining_time":0.679463788},
{"learn":[0.09793638554],"iteration":872,"passed_time":4.631144246,"remaining_time":0.6737174332},
{"learn":[0.09784777955],"iteration":873,"passed_time":4.633691175,"remaining_time":0.668014975},
{"learn":[0.09773978038],"iteration":874,"passed_time":4.636195291,"remaining_time":0.662313613},
{"learn":[0.09761977971],"iteration":875,"passed_time":4.638848992,"remaining_time":0.6566407249},
{"learn":[0.09751501188],"iteration":876,"passed_time":4.657205448,"remaining_time":0.6531770469},
{"learn":[0.09738949041],"iteration":877,"passed_time":4.673078961,"remaining_time":0.6493344342},
{"learn":[0.09720191592],"iteration":878,"passed_time":4.675977027,"remaining_time":0.6436782939},
{"learn":[0.09710641359],"iteration":879,"passed_time":4.679232863,"remaining_time":0.6380772086},
{"learn":[0.09700665516],"iteration":880,"passed_time":4.68155177,"remaining_time":0.6323548929},
{"learn":[0.09691414374],"iteration":881,"passed_time":4.687359185,"remaining_time":0.6271070112},
{"learn":[0.09685408788],"iteration":882,"passed_time":4.691017489,"remaining_time":0.6215730987},
{"learn":[0.096680548],"iteration":883,"passed_time":4.694549602,"remaining_time":0.6160268708},
{"learn":[0.09652077995],"iteration":884,"passed_time":4.697674788,"remaining_time":0.6104323171},
{"learn":[0.09640772452],"iteration":885,"passed_time":4.702687658,"remaining_time":0.6050862223},
{"learn":[0.09635284665],"iteration":886,"passed_time":4.705906089,"remaining_time":0.5995122751},
{"learn":[0.0962636487],"iteration":887,"passed_time":4.717690339,"remaining_time":0.5950240067},
{"learn":[0.09623567924],"iteration":888,"passed_time":4.72024793,"remaining_time":0.5893672893},
{"learn":[0.09617623407],"iteration":889,"passed_time":4.733746048,"remaining_time":0.5850697363},
{"learn":[0.09608253493],"iteration":890,"passed_time":4.736872147,"remaining_time":0.5794826756},
{"learn":[0.09601611792],"iteration":891,"passed_time":4.749093974,"remaining_time":0.5750024094},
{"learn":[0.09589855276],"iteration":892,"passed_time":4.763950726,"remaining_time":0.5708205238},
{"learn":[0.09587033856],"iteration":893,"passed_time":4.779534099,"remaining_time":0.5667009111},
{"learn":[0.09581003343],"iteration":894,"passed_time":4.794772738,"remaining_time":0.5625152374},
{"learn":[0.09572663492],"iteration":895,"passed_time":4.797302915,"remaining_time":0.5568298027},
{"learn":[0.09563036257],"iteration":896,"passed_time":4.799781796,"remaining_time":0.5511455128},
{"learn":[0.09557417946],"iteration":897,"passed_time":4.802496347,"remaining_time":0.5454951307},
{"learn":[0.09547446169],"iteration":898,"passed_time":4.804756909,"remaining_time":0.5398002757},
{"learn":[0.09535821709],"iteration":899,"passed_time":4.807002201,"remaining_time":0.5341113557},
{"learn":[0.09529815434],"iteration":900,"passed_time":4.809463671,"remaining_time":0.5284538329},
{"learn":[0.09524672735],"iteration":901,"passed_time":4.811670853,"remaining_time":0.5227757689},
{"learn":[0.09510371538],"iteration":902,"passed_time":4.814114894,"remaining_time":0.5171308358},
{"learn":[0.09496379187],"iteration":903,"passed_time":4.816454293,"remaining_time":0.5114818718},
{"learn":[0.09490666016],"iteration":904,"passed_time":4.818888409,"remaining_time":0.5058501645},
{"learn":[0.09481257451],"iteration":905,"passed_time":4.821516259,"remaining_time":0.5002456163},
{"learn":[0.09467582776],"iteration":906,"passed_time":4.823975545,"remaining_time":0.494630348},
{"learn":[0.09462835937],"iteration":907,"passed_time":4.840252974,"remaining_time":0.4904221075},
{"learn":[0.0945460451],"iteration":908,"passed_time":4.842695437,"remaining_time":0.4848022934},
{"learn":[0.09449637581],"iteration":909,"passed_time":4.845362956,"remaining_time":0.4792117209},
{"learn":[0.09442355202],"iteration":910,"passed_time":4.847768781,"remaining_time":0.4736019995},
{"learn":[0.09434409371],"iteration":911,"passed_time":4.850496379,"remaining_time":0.4680303524},
{"learn":[0.09424042197],"iteration":912,"passed_time":4.852895947,"remaining_time":0.4624336773},
{"learn":[0.094138993],"iteration":913,"passed_time":4.855764364,"remaining_time":0.456888113},
{"learn":[0.09405526776],"iteration":914,"passed_time":4.858146572,"remaining_time":0.4513032335},
{"learn":[0.09395512807],"iteration":915,"passed_time":4.871184609,"remaining_time":0.4467025187},
{"learn":[0.09381058249],"iteration":916,"passed_time":4.873797398,"remaining_time":0.4411397863},
{"learn":[0.09374478136],"iteration":917,"passed_time":4.886111194,"remaining_time":0.4364500195},
{"learn":[0.09366099629],"iteration":918,"passed_time":4.888821864,"remaining_time":0.4308972481},
{"learn":[0.09350723062],"iteration":919,"passed_time":4.89177558,"remaining_time":0.4253717896},
{"learn":[0.0934156111],"iteration":920,"passed_time":4.900890072,"remaining_time":0.4203803645},
{"learn":[0.09333322823],"iteration":921,"passed_time":4.916520728,"remaining_time":0.4159312547},
{"learn":[0.09328452138],"iteration":922,"passed_time":4.932133865,"remaining_time":0.4114564546},
{"learn":[0.09317503932],"iteration":923,"passed_time":4.94671205,"remaining_time":0.4068724197},
{"learn":[0.09308820969],"iteration":924,"passed_time":4.948977351,"remaining_time":0.4012684339},
{"learn":[0.09299792665],"iteration":925,"passed_time":4.951748025,"remaining_time":0.3957120452},
{"learn":[0.0929459736],"iteration":926,"passed_time":4.962223705,"remaining_time":0.3907684255},
{"learn":[0.09285457343],"iteration":927,"passed_time":4.976878999,"remaining_time":0.3861371637},
{"learn":[0.09278334602],"iteration":928,"passed_time":4.992222115,"remaining_time":0.3815368893},
{"learn":[0.09268733402],"iteration":929,"passed_time":5.00688126,"remaining_time":0.3768620303},
{"learn":[0.09261352148],"iteration":930,"passed_time":5.009168595,"remaining_time":0.3712488003},
{"learn":[0.09252249436],"iteration":931,"passed_time":5.011548374,"remaining_time":0.3656494521},
{"learn":[0.09243891657],"iteration":932,"passed_time":5.022698672,"remaining_time":0.3606868285},
{"learn":[0.09229985537],"iteration":933,"passed_time":5.025115043,"remaining_time":0.3550937825},
{"learn":[0.0922115031],"iteration":934,"passed_time":5.027603116,"remaining_time":0.3495125161},
{"learn":[0.09211865075],"iteration":935,"passed_time":5.029910852,"remaining_time":0.3439255283},
{"learn":[0.09207086605],"iteration":936,"passed_time":5.032639468,"remaining_time":0.3383738383},
{"learn":[0.0919677604],"iteration":937,"passed_time":5.035208365,"remaining_time":0.3328176105},
{"learn":[0.09188940138],"iteration":938,"passed_time":5.037668128,"remaining_time":0.3272606558},
{"learn":[0.09171119418],"iteration":939,"passed_time":5.040008117,"remaining_time":0.3217026458},
{"learn":[0.09162664964],"iteration":940,"passed_time":5.042298388,"remaining_time":0.316148358},
{"learn":[0.0915875391],"iteration":941,"passed_time":5.044307777,"remaining_time":0.310583706},
{"learn":[0.09149313136],"iteration":942,"passed_time":5.046797604,"remaining_time":0.3050556346},
{"learn":[0.09142577693],"iteration":943,"passed_time":5.049241083,"remaining_time":0.2995312507},
{"learn":[0.09136697491],"iteration":944,"passed_time":5.051931898,"remaining_time":0.2940277824},
{"learn":[0.09122565533],"iteration":945,"passed_time":5.06986487,"remaining_time":0.2894003203},
{"learn":[0.09117010374],"iteration":946,"passed_time":5.072872553,"remaining_time":0.283909446},
{"learn":[0.09112392386],"iteration":947,"passed_time":5.083888054,"remaining_time":0.2788630578},
{"learn":[0.09106252209],"iteration":948,"passed_time":5.097008253,"remaining_time":0.273917198},
{"learn":[0.09092603925],"iteration":949,"passed_time":5.099309756,"remaining_time":0.268384724},
{"learn":[0.09087391226],"iteration":950,"passed_time":5.101373498,"remaining_time":0.2628467943},
{"learn":[0.09074276518],"iteration":951,"passed_time":5.10389667,"remaining_time":0.2573393279},
{"learn":[0.09064146758],"iteration":952,"passed_time":5.106282356,"remaining_time":0.2518313439},
{"learn":[0.09057569927],"iteration":953,"passed_time":5.108827868,"remaining_time":0.2463376121},
{"learn":[0.09048801874],"iteration":954,"passed_time":5.111471399,"remaining_time":0.2408546733},
{"learn":[0.09040110889],"iteration":955,"passed_time":5.113844284,"remaining_time":0.2353652181},
{"learn":[0.0903335258],"iteration":956,"passed_time":5.116281672,"remaining_time":0.2298851744},
{"learn":[0.09024023983],"iteration":957,"passed_time":5.118746413,"remaining_time":0.224412682},
{"learn":[0.09016595334],"iteration":958,"passed_time":5.121215269,"remaining_time":0.2189466382},
{"learn":[0.08998177309],"iteration":959,"passed_time":5.123553505,"remaining_time":0.213481396},
{"learn":[0.08990417456],"iteration":960,"passed_time":5.125833401,"remaining_time":0.2080202941},
{"learn":[0.08980460928],"iteration":961,"passed_time":5.128109244,"remaining_time":0.2025656458},
{"learn":[0.08968002687],"iteration":962,"passed_time":5.130280152,"remaining_time":0.1971135676},
{"learn":[0.08959878462],"iteration":963,"passed_time":5.132707715,"remaining_time":0.1916778815},
{"learn":[0.0895026957],"iteration":964,"passed_time":5.134899046,"remaining_time":0.1862398618},
{"learn":[0.08941908428],"iteration":965,"passed_time":5.137283658,"remaining_time":0.1808153669},
{"learn":[0.08934110206],"iteration":966,"passed_time":5.139478304,"remaining_time":0.1753906764},
{"learn":[0.08923169757],"iteration":967,"passed_time":5.141696277,"remaining_time":0.1699734307},
{"learn":[0.08900512842],"iteration":968,"passed_time":5.144211771,"remaining_time":0.1645723064},
{"learn":[0.08887749896],"iteration":969,"passed_time":5.14677161,"remaining_time":0.1591785034},
{"learn":[0.08876457676],"iteration":970,"passed_time":5.149085714,"remaining_time":0.1537831985},
{"learn":[0.08864787216],"iteration":971,"passed_time":5.151339658,"remaining_time":0.1483925004},
{"learn":[0.08858885575],"iteration":972,"passed_time":5.153505056,"remaining_time":0.1430057929},
{"learn":[0.08847580079],"iteration":973,"passed_time":5.156151684,"remaining_time":0.137638546},
{"learn":[0.08840178984],"iteration":974,"passed_time":5.158515992,"remaining_time":0.1322696408},
{"learn":[0.08830119577],"iteration":975,"passed_time":5.160961086,"remaining_time":0.1269088792},
{"learn":[0.08824042629],"iteration":976,"passed_time":5.163228311,"remaining_time":0.1215498988},
{"learn":[0.08815600848],"iteration":977,"passed_time":5.165441089,"remaining_time":0.1161960163},
{"learn":[0.08808172199],"iteration":978,"passed_time":5.167894577,"remaining_time":0.1108537141},
{"learn":[0.08798993526],"iteration":979,"passed_time":5.170114639,"remaining_time":0.1055125437},
{"learn":[0.08789008075],"iteration":980,"passed_time":5.172326234,"remaining_time":0.1001775723},
{"learn":[0.08769755677],"iteration":981,"passed_time":5.174563239,"remaining_time":0.09484942801},
{"learn":[0.08760225856],"iteration":982,"passed_time":5.177221149,"remaining_time":0.08953485202},
{"learn":[0.08742846842],"iteration":983,"passed_time":5.186154727,"remaining_time":0.08432771914},
{"learn":[0.087349943],"iteration":984,"passed_time":5.188505844,"remaining_time":0.07901277935},
{"learn":[0.0872774604],"iteration":985,"passed_time":5.190964499,"remaining_time":0.07370537828},
{"learn":[0.08726026496],"iteration":986,"passed_time":5.201991713,"remaining_time":0.06851660817},
{"learn":[0.08717785582],"iteration":987,"passed_time":5.216706138,"remaining_time":0.06336080329},
{"learn":[0.08709107829],"iteration":988,"passed_time":5.234367396,"remaining_time":0.05821844424},
{"learn":[0.08701392914],"iteration":989,"passed_time":5.247834948,"remaining_time":0.05300843382},
{"learn":[0.08694806762],"iteration":990,"passed_time":5.263592151,"remaining_time":0.04780255233},
{"learn":[0.08686157568],"iteration":991,"passed_time":5.266216298,"remaining_time":0.04246948628},
{"learn":[0.08678827294],"iteration":992,"passed_time":5.268807742,"remaining_time":0.03714164571},
{"learn":[0.0867360347],"iteration":993,"passed_time":5.271263401,"remaining_time":0.03181849135},
{"learn":[0.08668351957],"iteration":994,"passed_time":5.274125005,"remaining_time":0.02650314073},
{"learn":[0.0865917685],"iteration":995,"passed_time":5.278037993,"remaining_time":0.02119693973},
{"learn":[0.08646590587],"iteration":996,"passed_time":5.280871281,"remaining_time":0.0158902847},
{"learn":[0.08642424777],"iteration":997,"passed_time":5.283348372,"remaining_time":0.01058787249},
{"learn":[0.08633150228],"iteration":998,"passed_time":5.285718221,"remaining_time":0.00529100923},
{"learn":[0.086300302],"iteration":999,"passed_time":5.288053616,"remaining_time":0}
]}